{"url":"https:\/\/4dpanda.com\/api\/fetchall","method":"GET","isAJAX":false,"startTime":1760363906.374947,"totalTime":89.1,"totalMemory":"1.457","segmentDuration":15,"segmentCount":6,"CI_VERSION":"4.5.1","collectors":[{"title":"Timers","titleSafe":"timers","titleDetails":"","display":[],"badgeValue":null,"isEmpty":false,"hasTabContent":false,"hasLabel":false,"icon":"","hasTimelineData":true,"timelineData":[{"name":"Bootstrap","component":"Timer","start":1760363906.375198,"duration":0.002073049545288086},{"name":"Required Before Filters","component":"Timer","start":1760363906.377273,"duration":0.012826919555664062},{"name":"Routing","component":"Timer","start":1760363906.39011,"duration":0.0012938976287841797},{"name":"Before Filters","component":"Timer","start":1760363906.391418,"duration":2.5987625122070312e-5},{"name":"Controller","component":"Timer","start":1760363906.391447,"duration":0.07249903678894043},{"name":"Controller Constructor","component":"Timer","start":1760363906.391447,"duration":0.0009579658508300781},{"name":"After Filters","component":"Timer","start":1760363906.463971,"duration":5.0067901611328125e-6},{"name":"Required After Filters","component":"Timer","start":1760363906.464004,"duration":0.00013399124145507812}]},{"title":"Database","titleSafe":"database","titleDetails":"(20 total Queries, 20 of them unique across 1 Connection)","display":{"queries":[{"hover":"","class":"","duration":"0.57 ms","sql":"<strong>SELECT<\/strong> *\n<strong>FROM<\/strong> `lottery_data`\n<strong>WHERE<\/strong> `type` = &#039;M4D&#039;\n<strong>ORDER<\/strong> <strong>BY<\/strong> `id` <strong>DESC<\/strong>\n <strong>LIMIT<\/strong> 1","trace":[{"file":"SYSTEMPATH\/Database\/BaseBuilder.php:1629","function":"\u00a0\u00a0\u00a0\u00a0\u00a0\u00a0\u00a0\u00a0CodeIgniter\\Database\\BaseConnection->query()","index":"\u00a0\u00a01\u00a0\u00a0\u00a0\u00a0"},{"file":"SYSTEMPATH\/Model.php:319","function":"\u00a0\u00a0\u00a0\u00a0\u00a0\u00a0\u00a0\u00a0CodeIgniter\\Database\\BaseBuilder->get()","index":"\u00a0\u00a02\u00a0\u00a0\u00a0\u00a0"},{"file":"SYSTEMPATH\/BaseModel.php:714","function":"\u00a0\u00a0\u00a0\u00a0\u00a0\u00a0\u00a0\u00a0CodeIgniter\\Model->doFirst()","index":"\u00a0\u00a03\u00a0\u00a0\u00a0\u00a0"},{"file":"APPPATH\/Models\/LotteryModel.php:23","function":"\u00a0\u00a0\u00a0\u00a0\u00a0\u00a0\u00a0\u00a0CodeIgniter\\BaseModel->first()","index":"\u00a0\u00a04\u00a0\u00a0\u00a0\u00a0"},{"file":"APPPATH\/Controllers\/LotteryData.php:51","function":"\u00a0\u00a0\u00a0\u00a0\u00a0\u00a0\u00a0\u00a0App\\Models\\LotteryModel->getLotteryDataByType()","index":"\u00a0\u00a05\u00a0\u00a0\u00a0\u00a0"},{"file":"SYSTEMPATH\/CodeIgniter.php:933","function":"\u00a0\u00a0\u00a0\u00a0\u00a0\u00a0\u00a0\u00a0App\\Controllers\\LotteryData->fetchAll()","index":"\u00a0\u00a06\u00a0\u00a0\u00a0\u00a0"},{"file":"SYSTEMPATH\/CodeIgniter.php:509","function":"\u00a0\u00a0\u00a0\u00a0\u00a0\u00a0\u00a0\u00a0CodeIgniter\\CodeIgniter->runController()","index":"\u00a0\u00a07\u00a0\u00a0\u00a0\u00a0"},{"file":"SYSTEMPATH\/CodeIgniter.php:355","function":"\u00a0\u00a0\u00a0\u00a0\u00a0\u00a0\u00a0\u00a0CodeIgniter\\CodeIgniter->handleRequest()","index":"\u00a0\u00a08\u00a0\u00a0\u00a0\u00a0"},{"file":"SYSTEMPATH\/Boot.php:312","function":"\u00a0\u00a0\u00a0\u00a0\u00a0\u00a0\u00a0\u00a0CodeIgniter\\CodeIgniter->run()","index":"\u00a0\u00a09\u00a0\u00a0\u00a0\u00a0"},{"file":"SYSTEMPATH\/Boot.php:67","function":"\u00a0\u00a0\u00a0\u00a0\u00a0\u00a0\u00a0\u00a0CodeIgniter\\Boot::runCodeIgniter()","index":"\u00a010\u00a0\u00a0\u00a0\u00a0"},{"file":"FCPATH\/index.php:56","function":"\u00a0\u00a0\u00a0\u00a0\u00a0\u00a0\u00a0\u00a0CodeIgniter\\Boot::bootWeb()","index":"\u00a011\u00a0\u00a0\u00a0\u00a0"}],"trace-file":"APPPATH\/Models\/LotteryModel.php:23","qid":"bc04587e61157dc85192600ec8a188da"},{"hover":"","class":"","duration":"0.51 ms","sql":"<strong>SELECT<\/strong> *\n<strong>FROM<\/strong> `lottery_data`\n<strong>WHERE<\/strong> `type` = &#039;DMC4D&#039;\n<strong>ORDER<\/strong> <strong>BY<\/strong> `id` <strong>DESC<\/strong>\n <strong>LIMIT<\/strong> 1","trace":[{"file":"SYSTEMPATH\/Database\/BaseBuilder.php:1629","function":"\u00a0\u00a0\u00a0\u00a0\u00a0\u00a0\u00a0\u00a0CodeIgniter\\Database\\BaseConnection->query()","index":"\u00a0\u00a01\u00a0\u00a0\u00a0\u00a0"},{"file":"SYSTEMPATH\/Model.php:319","function":"\u00a0\u00a0\u00a0\u00a0\u00a0\u00a0\u00a0\u00a0CodeIgniter\\Database\\BaseBuilder->get()","index":"\u00a0\u00a02\u00a0\u00a0\u00a0\u00a0"},{"file":"SYSTEMPATH\/BaseModel.php:714","function":"\u00a0\u00a0\u00a0\u00a0\u00a0\u00a0\u00a0\u00a0CodeIgniter\\Model->doFirst()","index":"\u00a0\u00a03\u00a0\u00a0\u00a0\u00a0"},{"file":"APPPATH\/Models\/LotteryModel.php:23","function":"\u00a0\u00a0\u00a0\u00a0\u00a0\u00a0\u00a0\u00a0CodeIgniter\\BaseModel->first()","index":"\u00a0\u00a04\u00a0\u00a0\u00a0\u00a0"},{"file":"APPPATH\/Controllers\/LotteryData.php:51","function":"\u00a0\u00a0\u00a0\u00a0\u00a0\u00a0\u00a0\u00a0App\\Models\\LotteryModel->getLotteryDataByType()","index":"\u00a0\u00a05\u00a0\u00a0\u00a0\u00a0"},{"file":"SYSTEMPATH\/CodeIgniter.php:933","function":"\u00a0\u00a0\u00a0\u00a0\u00a0\u00a0\u00a0\u00a0App\\Controllers\\LotteryData->fetchAll()","index":"\u00a0\u00a06\u00a0\u00a0\u00a0\u00a0"},{"file":"SYSTEMPATH\/CodeIgniter.php:509","function":"\u00a0\u00a0\u00a0\u00a0\u00a0\u00a0\u00a0\u00a0CodeIgniter\\CodeIgniter->runController()","index":"\u00a0\u00a07\u00a0\u00a0\u00a0\u00a0"},{"file":"SYSTEMPATH\/CodeIgniter.php:355","function":"\u00a0\u00a0\u00a0\u00a0\u00a0\u00a0\u00a0\u00a0CodeIgniter\\CodeIgniter->handleRequest()","index":"\u00a0\u00a08\u00a0\u00a0\u00a0\u00a0"},{"file":"SYSTEMPATH\/Boot.php:312","function":"\u00a0\u00a0\u00a0\u00a0\u00a0\u00a0\u00a0\u00a0CodeIgniter\\CodeIgniter->run()","index":"\u00a0\u00a09\u00a0\u00a0\u00a0\u00a0"},{"file":"SYSTEMPATH\/Boot.php:67","function":"\u00a0\u00a0\u00a0\u00a0\u00a0\u00a0\u00a0\u00a0CodeIgniter\\Boot::runCodeIgniter()","index":"\u00a010\u00a0\u00a0\u00a0\u00a0"},{"file":"FCPATH\/index.php:56","function":"\u00a0\u00a0\u00a0\u00a0\u00a0\u00a0\u00a0\u00a0CodeIgniter\\Boot::bootWeb()","index":"\u00a011\u00a0\u00a0\u00a0\u00a0"}],"trace-file":"APPPATH\/Models\/LotteryModel.php:23","qid":"8b26be088e86dac07dfe48cc639d2a72"},{"hover":"","class":"","duration":"0.47 ms","sql":"<strong>SELECT<\/strong> *\n<strong>FROM<\/strong> `lottery_data`\n<strong>WHERE<\/strong> `type` = &#039;DMC6D&#039;\n<strong>ORDER<\/strong> <strong>BY<\/strong> `id` <strong>DESC<\/strong>\n <strong>LIMIT<\/strong> 1","trace":[{"file":"SYSTEMPATH\/Database\/BaseBuilder.php:1629","function":"\u00a0\u00a0\u00a0\u00a0\u00a0\u00a0\u00a0\u00a0CodeIgniter\\Database\\BaseConnection->query()","index":"\u00a0\u00a01\u00a0\u00a0\u00a0\u00a0"},{"file":"SYSTEMPATH\/Model.php:319","function":"\u00a0\u00a0\u00a0\u00a0\u00a0\u00a0\u00a0\u00a0CodeIgniter\\Database\\BaseBuilder->get()","index":"\u00a0\u00a02\u00a0\u00a0\u00a0\u00a0"},{"file":"SYSTEMPATH\/BaseModel.php:714","function":"\u00a0\u00a0\u00a0\u00a0\u00a0\u00a0\u00a0\u00a0CodeIgniter\\Model->doFirst()","index":"\u00a0\u00a03\u00a0\u00a0\u00a0\u00a0"},{"file":"APPPATH\/Models\/LotteryModel.php:23","function":"\u00a0\u00a0\u00a0\u00a0\u00a0\u00a0\u00a0\u00a0CodeIgniter\\BaseModel->first()","index":"\u00a0\u00a04\u00a0\u00a0\u00a0\u00a0"},{"file":"APPPATH\/Controllers\/LotteryData.php:51","function":"\u00a0\u00a0\u00a0\u00a0\u00a0\u00a0\u00a0\u00a0App\\Models\\LotteryModel->getLotteryDataByType()","index":"\u00a0\u00a05\u00a0\u00a0\u00a0\u00a0"},{"file":"SYSTEMPATH\/CodeIgniter.php:933","function":"\u00a0\u00a0\u00a0\u00a0\u00a0\u00a0\u00a0\u00a0App\\Controllers\\LotteryData->fetchAll()","index":"\u00a0\u00a06\u00a0\u00a0\u00a0\u00a0"},{"file":"SYSTEMPATH\/CodeIgniter.php:509","function":"\u00a0\u00a0\u00a0\u00a0\u00a0\u00a0\u00a0\u00a0CodeIgniter\\CodeIgniter->runController()","index":"\u00a0\u00a07\u00a0\u00a0\u00a0\u00a0"},{"file":"SYSTEMPATH\/CodeIgniter.php:355","function":"\u00a0\u00a0\u00a0\u00a0\u00a0\u00a0\u00a0\u00a0CodeIgniter\\CodeIgniter->handleRequest()","index":"\u00a0\u00a08\u00a0\u00a0\u00a0\u00a0"},{"file":"SYSTEMPATH\/Boot.php:312","function":"\u00a0\u00a0\u00a0\u00a0\u00a0\u00a0\u00a0\u00a0CodeIgniter\\CodeIgniter->run()","index":"\u00a0\u00a09\u00a0\u00a0\u00a0\u00a0"},{"file":"SYSTEMPATH\/Boot.php:67","function":"\u00a0\u00a0\u00a0\u00a0\u00a0\u00a0\u00a0\u00a0CodeIgniter\\Boot::runCodeIgniter()","index":"\u00a010\u00a0\u00a0\u00a0\u00a0"},{"file":"FCPATH\/index.php:56","function":"\u00a0\u00a0\u00a0\u00a0\u00a0\u00a0\u00a0\u00a0CodeIgniter\\Boot::bootWeb()","index":"\u00a011\u00a0\u00a0\u00a0\u00a0"}],"trace-file":"APPPATH\/Models\/LotteryModel.php:23","qid":"b2bdc83f0a0b351bdce91355cba9a3f5"},{"hover":"","class":"","duration":"1.17 ms","sql":"<strong>SELECT<\/strong> *\n<strong>FROM<\/strong> `lottery_data`\n<strong>WHERE<\/strong> `type` = &#039;TT&#039;\n<strong>ORDER<\/strong> <strong>BY<\/strong> `id` <strong>DESC<\/strong>\n <strong>LIMIT<\/strong> 1","trace":[{"file":"SYSTEMPATH\/Database\/BaseBuilder.php:1629","function":"\u00a0\u00a0\u00a0\u00a0\u00a0\u00a0\u00a0\u00a0CodeIgniter\\Database\\BaseConnection->query()","index":"\u00a0\u00a01\u00a0\u00a0\u00a0\u00a0"},{"file":"SYSTEMPATH\/Model.php:319","function":"\u00a0\u00a0\u00a0\u00a0\u00a0\u00a0\u00a0\u00a0CodeIgniter\\Database\\BaseBuilder->get()","index":"\u00a0\u00a02\u00a0\u00a0\u00a0\u00a0"},{"file":"SYSTEMPATH\/BaseModel.php:714","function":"\u00a0\u00a0\u00a0\u00a0\u00a0\u00a0\u00a0\u00a0CodeIgniter\\Model->doFirst()","index":"\u00a0\u00a03\u00a0\u00a0\u00a0\u00a0"},{"file":"APPPATH\/Models\/LotteryModel.php:23","function":"\u00a0\u00a0\u00a0\u00a0\u00a0\u00a0\u00a0\u00a0CodeIgniter\\BaseModel->first()","index":"\u00a0\u00a04\u00a0\u00a0\u00a0\u00a0"},{"file":"APPPATH\/Controllers\/LotteryData.php:51","function":"\u00a0\u00a0\u00a0\u00a0\u00a0\u00a0\u00a0\u00a0App\\Models\\LotteryModel->getLotteryDataByType()","index":"\u00a0\u00a05\u00a0\u00a0\u00a0\u00a0"},{"file":"SYSTEMPATH\/CodeIgniter.php:933","function":"\u00a0\u00a0\u00a0\u00a0\u00a0\u00a0\u00a0\u00a0App\\Controllers\\LotteryData->fetchAll()","index":"\u00a0\u00a06\u00a0\u00a0\u00a0\u00a0"},{"file":"SYSTEMPATH\/CodeIgniter.php:509","function":"\u00a0\u00a0\u00a0\u00a0\u00a0\u00a0\u00a0\u00a0CodeIgniter\\CodeIgniter->runController()","index":"\u00a0\u00a07\u00a0\u00a0\u00a0\u00a0"},{"file":"SYSTEMPATH\/CodeIgniter.php:355","function":"\u00a0\u00a0\u00a0\u00a0\u00a0\u00a0\u00a0\u00a0CodeIgniter\\CodeIgniter->handleRequest()","index":"\u00a0\u00a08\u00a0\u00a0\u00a0\u00a0"},{"file":"SYSTEMPATH\/Boot.php:312","function":"\u00a0\u00a0\u00a0\u00a0\u00a0\u00a0\u00a0\u00a0CodeIgniter\\CodeIgniter->run()","index":"\u00a0\u00a09\u00a0\u00a0\u00a0\u00a0"},{"file":"SYSTEMPATH\/Boot.php:67","function":"\u00a0\u00a0\u00a0\u00a0\u00a0\u00a0\u00a0\u00a0CodeIgniter\\Boot::runCodeIgniter()","index":"\u00a010\u00a0\u00a0\u00a0\u00a0"},{"file":"FCPATH\/index.php:56","function":"\u00a0\u00a0\u00a0\u00a0\u00a0\u00a0\u00a0\u00a0CodeIgniter\\Boot::bootWeb()","index":"\u00a011\u00a0\u00a0\u00a0\u00a0"}],"trace-file":"APPPATH\/Models\/LotteryModel.php:23","qid":"46c55a919dfc8a0df58dcf97220a6861"},{"hover":"","class":"","duration":"0.44 ms","sql":"<strong>SELECT<\/strong> *\n<strong>FROM<\/strong> `lottery_data`\n<strong>WHERE<\/strong> `type` = &#039;STC&#039;\n<strong>ORDER<\/strong> <strong>BY<\/strong> `id` <strong>DESC<\/strong>\n <strong>LIMIT<\/strong> 1","trace":[{"file":"SYSTEMPATH\/Database\/BaseBuilder.php:1629","function":"\u00a0\u00a0\u00a0\u00a0\u00a0\u00a0\u00a0\u00a0CodeIgniter\\Database\\BaseConnection->query()","index":"\u00a0\u00a01\u00a0\u00a0\u00a0\u00a0"},{"file":"SYSTEMPATH\/Model.php:319","function":"\u00a0\u00a0\u00a0\u00a0\u00a0\u00a0\u00a0\u00a0CodeIgniter\\Database\\BaseBuilder->get()","index":"\u00a0\u00a02\u00a0\u00a0\u00a0\u00a0"},{"file":"SYSTEMPATH\/BaseModel.php:714","function":"\u00a0\u00a0\u00a0\u00a0\u00a0\u00a0\u00a0\u00a0CodeIgniter\\Model->doFirst()","index":"\u00a0\u00a03\u00a0\u00a0\u00a0\u00a0"},{"file":"APPPATH\/Models\/LotteryModel.php:23","function":"\u00a0\u00a0\u00a0\u00a0\u00a0\u00a0\u00a0\u00a0CodeIgniter\\BaseModel->first()","index":"\u00a0\u00a04\u00a0\u00a0\u00a0\u00a0"},{"file":"APPPATH\/Controllers\/LotteryData.php:51","function":"\u00a0\u00a0\u00a0\u00a0\u00a0\u00a0\u00a0\u00a0App\\Models\\LotteryModel->getLotteryDataByType()","index":"\u00a0\u00a05\u00a0\u00a0\u00a0\u00a0"},{"file":"SYSTEMPATH\/CodeIgniter.php:933","function":"\u00a0\u00a0\u00a0\u00a0\u00a0\u00a0\u00a0\u00a0App\\Controllers\\LotteryData->fetchAll()","index":"\u00a0\u00a06\u00a0\u00a0\u00a0\u00a0"},{"file":"SYSTEMPATH\/CodeIgniter.php:509","function":"\u00a0\u00a0\u00a0\u00a0\u00a0\u00a0\u00a0\u00a0CodeIgniter\\CodeIgniter->runController()","index":"\u00a0\u00a07\u00a0\u00a0\u00a0\u00a0"},{"file":"SYSTEMPATH\/CodeIgniter.php:355","function":"\u00a0\u00a0\u00a0\u00a0\u00a0\u00a0\u00a0\u00a0CodeIgniter\\CodeIgniter->handleRequest()","index":"\u00a0\u00a08\u00a0\u00a0\u00a0\u00a0"},{"file":"SYSTEMPATH\/Boot.php:312","function":"\u00a0\u00a0\u00a0\u00a0\u00a0\u00a0\u00a0\u00a0CodeIgniter\\CodeIgniter->run()","index":"\u00a0\u00a09\u00a0\u00a0\u00a0\u00a0"},{"file":"SYSTEMPATH\/Boot.php:67","function":"\u00a0\u00a0\u00a0\u00a0\u00a0\u00a0\u00a0\u00a0CodeIgniter\\Boot::runCodeIgniter()","index":"\u00a010\u00a0\u00a0\u00a0\u00a0"},{"file":"FCPATH\/index.php:56","function":"\u00a0\u00a0\u00a0\u00a0\u00a0\u00a0\u00a0\u00a0CodeIgniter\\Boot::bootWeb()","index":"\u00a011\u00a0\u00a0\u00a0\u00a0"}],"trace-file":"APPPATH\/Models\/LotteryModel.php:23","qid":"99601680cd6e0e9c9cb4770ec6cb99cd"},{"hover":"","class":"","duration":"0.34 ms","sql":"<strong>SELECT<\/strong> *\n<strong>FROM<\/strong> `lottery_data`\n<strong>WHERE<\/strong> `type` = &#039;SB&#039;\n<strong>ORDER<\/strong> <strong>BY<\/strong> `id` <strong>DESC<\/strong>\n <strong>LIMIT<\/strong> 1","trace":[{"file":"SYSTEMPATH\/Database\/BaseBuilder.php:1629","function":"\u00a0\u00a0\u00a0\u00a0\u00a0\u00a0\u00a0\u00a0CodeIgniter\\Database\\BaseConnection->query()","index":"\u00a0\u00a01\u00a0\u00a0\u00a0\u00a0"},{"file":"SYSTEMPATH\/Model.php:319","function":"\u00a0\u00a0\u00a0\u00a0\u00a0\u00a0\u00a0\u00a0CodeIgniter\\Database\\BaseBuilder->get()","index":"\u00a0\u00a02\u00a0\u00a0\u00a0\u00a0"},{"file":"SYSTEMPATH\/BaseModel.php:714","function":"\u00a0\u00a0\u00a0\u00a0\u00a0\u00a0\u00a0\u00a0CodeIgniter\\Model->doFirst()","index":"\u00a0\u00a03\u00a0\u00a0\u00a0\u00a0"},{"file":"APPPATH\/Models\/LotteryModel.php:23","function":"\u00a0\u00a0\u00a0\u00a0\u00a0\u00a0\u00a0\u00a0CodeIgniter\\BaseModel->first()","index":"\u00a0\u00a04\u00a0\u00a0\u00a0\u00a0"},{"file":"APPPATH\/Controllers\/LotteryData.php:51","function":"\u00a0\u00a0\u00a0\u00a0\u00a0\u00a0\u00a0\u00a0App\\Models\\LotteryModel->getLotteryDataByType()","index":"\u00a0\u00a05\u00a0\u00a0\u00a0\u00a0"},{"file":"SYSTEMPATH\/CodeIgniter.php:933","function":"\u00a0\u00a0\u00a0\u00a0\u00a0\u00a0\u00a0\u00a0App\\Controllers\\LotteryData->fetchAll()","index":"\u00a0\u00a06\u00a0\u00a0\u00a0\u00a0"},{"file":"SYSTEMPATH\/CodeIgniter.php:509","function":"\u00a0\u00a0\u00a0\u00a0\u00a0\u00a0\u00a0\u00a0CodeIgniter\\CodeIgniter->runController()","index":"\u00a0\u00a07\u00a0\u00a0\u00a0\u00a0"},{"file":"SYSTEMPATH\/CodeIgniter.php:355","function":"\u00a0\u00a0\u00a0\u00a0\u00a0\u00a0\u00a0\u00a0CodeIgniter\\CodeIgniter->handleRequest()","index":"\u00a0\u00a08\u00a0\u00a0\u00a0\u00a0"},{"file":"SYSTEMPATH\/Boot.php:312","function":"\u00a0\u00a0\u00a0\u00a0\u00a0\u00a0\u00a0\u00a0CodeIgniter\\CodeIgniter->run()","index":"\u00a0\u00a09\u00a0\u00a0\u00a0\u00a0"},{"file":"SYSTEMPATH\/Boot.php:67","function":"\u00a0\u00a0\u00a0\u00a0\u00a0\u00a0\u00a0\u00a0CodeIgniter\\Boot::runCodeIgniter()","index":"\u00a010\u00a0\u00a0\u00a0\u00a0"},{"file":"FCPATH\/index.php:56","function":"\u00a0\u00a0\u00a0\u00a0\u00a0\u00a0\u00a0\u00a0CodeIgniter\\Boot::bootWeb()","index":"\u00a011\u00a0\u00a0\u00a0\u00a0"}],"trace-file":"APPPATH\/Models\/LotteryModel.php:23","qid":"dc0da5ed8922edfe1f5c400b087ad212"},{"hover":"","class":"","duration":"5.24 ms","sql":"<strong>SELECT<\/strong> *\n<strong>FROM<\/strong> `lottery_data`\n<strong>WHERE<\/strong> `type` = &#039;SBLT&#039;\n<strong>ORDER<\/strong> <strong>BY<\/strong> `id` <strong>DESC<\/strong>\n <strong>LIMIT<\/strong> 1","trace":[{"file":"SYSTEMPATH\/Database\/BaseBuilder.php:1629","function":"\u00a0\u00a0\u00a0\u00a0\u00a0\u00a0\u00a0\u00a0CodeIgniter\\Database\\BaseConnection->query()","index":"\u00a0\u00a01\u00a0\u00a0\u00a0\u00a0"},{"file":"SYSTEMPATH\/Model.php:319","function":"\u00a0\u00a0\u00a0\u00a0\u00a0\u00a0\u00a0\u00a0CodeIgniter\\Database\\BaseBuilder->get()","index":"\u00a0\u00a02\u00a0\u00a0\u00a0\u00a0"},{"file":"SYSTEMPATH\/BaseModel.php:714","function":"\u00a0\u00a0\u00a0\u00a0\u00a0\u00a0\u00a0\u00a0CodeIgniter\\Model->doFirst()","index":"\u00a0\u00a03\u00a0\u00a0\u00a0\u00a0"},{"file":"APPPATH\/Models\/LotteryModel.php:23","function":"\u00a0\u00a0\u00a0\u00a0\u00a0\u00a0\u00a0\u00a0CodeIgniter\\BaseModel->first()","index":"\u00a0\u00a04\u00a0\u00a0\u00a0\u00a0"},{"file":"APPPATH\/Controllers\/LotteryData.php:51","function":"\u00a0\u00a0\u00a0\u00a0\u00a0\u00a0\u00a0\u00a0App\\Models\\LotteryModel->getLotteryDataByType()","index":"\u00a0\u00a05\u00a0\u00a0\u00a0\u00a0"},{"file":"SYSTEMPATH\/CodeIgniter.php:933","function":"\u00a0\u00a0\u00a0\u00a0\u00a0\u00a0\u00a0\u00a0App\\Controllers\\LotteryData->fetchAll()","index":"\u00a0\u00a06\u00a0\u00a0\u00a0\u00a0"},{"file":"SYSTEMPATH\/CodeIgniter.php:509","function":"\u00a0\u00a0\u00a0\u00a0\u00a0\u00a0\u00a0\u00a0CodeIgniter\\CodeIgniter->runController()","index":"\u00a0\u00a07\u00a0\u00a0\u00a0\u00a0"},{"file":"SYSTEMPATH\/CodeIgniter.php:355","function":"\u00a0\u00a0\u00a0\u00a0\u00a0\u00a0\u00a0\u00a0CodeIgniter\\CodeIgniter->handleRequest()","index":"\u00a0\u00a08\u00a0\u00a0\u00a0\u00a0"},{"file":"SYSTEMPATH\/Boot.php:312","function":"\u00a0\u00a0\u00a0\u00a0\u00a0\u00a0\u00a0\u00a0CodeIgniter\\CodeIgniter->run()","index":"\u00a0\u00a09\u00a0\u00a0\u00a0\u00a0"},{"file":"SYSTEMPATH\/Boot.php:67","function":"\u00a0\u00a0\u00a0\u00a0\u00a0\u00a0\u00a0\u00a0CodeIgniter\\Boot::runCodeIgniter()","index":"\u00a010\u00a0\u00a0\u00a0\u00a0"},{"file":"FCPATH\/index.php:56","function":"\u00a0\u00a0\u00a0\u00a0\u00a0\u00a0\u00a0\u00a0CodeIgniter\\Boot::bootWeb()","index":"\u00a011\u00a0\u00a0\u00a0\u00a0"}],"trace-file":"APPPATH\/Models\/LotteryModel.php:23","qid":"e3c38516d06c6038c3e6ad52d6ed77ab"},{"hover":"","class":"","duration":"0.56 ms","sql":"<strong>SELECT<\/strong> *\n<strong>FROM<\/strong> `lottery_data`\n<strong>WHERE<\/strong> `type` = &#039;SCS&#039;\n<strong>ORDER<\/strong> <strong>BY<\/strong> `id` <strong>DESC<\/strong>\n <strong>LIMIT<\/strong> 1","trace":[{"file":"SYSTEMPATH\/Database\/BaseBuilder.php:1629","function":"\u00a0\u00a0\u00a0\u00a0\u00a0\u00a0\u00a0\u00a0CodeIgniter\\Database\\BaseConnection->query()","index":"\u00a0\u00a01\u00a0\u00a0\u00a0\u00a0"},{"file":"SYSTEMPATH\/Model.php:319","function":"\u00a0\u00a0\u00a0\u00a0\u00a0\u00a0\u00a0\u00a0CodeIgniter\\Database\\BaseBuilder->get()","index":"\u00a0\u00a02\u00a0\u00a0\u00a0\u00a0"},{"file":"SYSTEMPATH\/BaseModel.php:714","function":"\u00a0\u00a0\u00a0\u00a0\u00a0\u00a0\u00a0\u00a0CodeIgniter\\Model->doFirst()","index":"\u00a0\u00a03\u00a0\u00a0\u00a0\u00a0"},{"file":"APPPATH\/Models\/LotteryModel.php:23","function":"\u00a0\u00a0\u00a0\u00a0\u00a0\u00a0\u00a0\u00a0CodeIgniter\\BaseModel->first()","index":"\u00a0\u00a04\u00a0\u00a0\u00a0\u00a0"},{"file":"APPPATH\/Controllers\/LotteryData.php:51","function":"\u00a0\u00a0\u00a0\u00a0\u00a0\u00a0\u00a0\u00a0App\\Models\\LotteryModel->getLotteryDataByType()","index":"\u00a0\u00a05\u00a0\u00a0\u00a0\u00a0"},{"file":"SYSTEMPATH\/CodeIgniter.php:933","function":"\u00a0\u00a0\u00a0\u00a0\u00a0\u00a0\u00a0\u00a0App\\Controllers\\LotteryData->fetchAll()","index":"\u00a0\u00a06\u00a0\u00a0\u00a0\u00a0"},{"file":"SYSTEMPATH\/CodeIgniter.php:509","function":"\u00a0\u00a0\u00a0\u00a0\u00a0\u00a0\u00a0\u00a0CodeIgniter\\CodeIgniter->runController()","index":"\u00a0\u00a07\u00a0\u00a0\u00a0\u00a0"},{"file":"SYSTEMPATH\/CodeIgniter.php:355","function":"\u00a0\u00a0\u00a0\u00a0\u00a0\u00a0\u00a0\u00a0CodeIgniter\\CodeIgniter->handleRequest()","index":"\u00a0\u00a08\u00a0\u00a0\u00a0\u00a0"},{"file":"SYSTEMPATH\/Boot.php:312","function":"\u00a0\u00a0\u00a0\u00a0\u00a0\u00a0\u00a0\u00a0CodeIgniter\\CodeIgniter->run()","index":"\u00a0\u00a09\u00a0\u00a0\u00a0\u00a0"},{"file":"SYSTEMPATH\/Boot.php:67","function":"\u00a0\u00a0\u00a0\u00a0\u00a0\u00a0\u00a0\u00a0CodeIgniter\\Boot::runCodeIgniter()","index":"\u00a010\u00a0\u00a0\u00a0\u00a0"},{"file":"FCPATH\/index.php:56","function":"\u00a0\u00a0\u00a0\u00a0\u00a0\u00a0\u00a0\u00a0CodeIgniter\\Boot::bootWeb()","index":"\u00a011\u00a0\u00a0\u00a0\u00a0"}],"trace-file":"APPPATH\/Models\/LotteryModel.php:23","qid":"2832cdb2e7a031cabb30e797d96b42c3"},{"hover":"","class":"","duration":"2.04 ms","sql":"<strong>SELECT<\/strong> *\n<strong>FROM<\/strong> `lottery_data`\n<strong>WHERE<\/strong> `type` = &#039;SGP4D&#039;\n<strong>ORDER<\/strong> <strong>BY<\/strong> `id` <strong>DESC<\/strong>\n <strong>LIMIT<\/strong> 1","trace":[{"file":"SYSTEMPATH\/Database\/BaseBuilder.php:1629","function":"\u00a0\u00a0\u00a0\u00a0\u00a0\u00a0\u00a0\u00a0CodeIgniter\\Database\\BaseConnection->query()","index":"\u00a0\u00a01\u00a0\u00a0\u00a0\u00a0"},{"file":"SYSTEMPATH\/Model.php:319","function":"\u00a0\u00a0\u00a0\u00a0\u00a0\u00a0\u00a0\u00a0CodeIgniter\\Database\\BaseBuilder->get()","index":"\u00a0\u00a02\u00a0\u00a0\u00a0\u00a0"},{"file":"SYSTEMPATH\/BaseModel.php:714","function":"\u00a0\u00a0\u00a0\u00a0\u00a0\u00a0\u00a0\u00a0CodeIgniter\\Model->doFirst()","index":"\u00a0\u00a03\u00a0\u00a0\u00a0\u00a0"},{"file":"APPPATH\/Models\/LotteryModel.php:23","function":"\u00a0\u00a0\u00a0\u00a0\u00a0\u00a0\u00a0\u00a0CodeIgniter\\BaseModel->first()","index":"\u00a0\u00a04\u00a0\u00a0\u00a0\u00a0"},{"file":"APPPATH\/Controllers\/LotteryData.php:51","function":"\u00a0\u00a0\u00a0\u00a0\u00a0\u00a0\u00a0\u00a0App\\Models\\LotteryModel->getLotteryDataByType()","index":"\u00a0\u00a05\u00a0\u00a0\u00a0\u00a0"},{"file":"SYSTEMPATH\/CodeIgniter.php:933","function":"\u00a0\u00a0\u00a0\u00a0\u00a0\u00a0\u00a0\u00a0App\\Controllers\\LotteryData->fetchAll()","index":"\u00a0\u00a06\u00a0\u00a0\u00a0\u00a0"},{"file":"SYSTEMPATH\/CodeIgniter.php:509","function":"\u00a0\u00a0\u00a0\u00a0\u00a0\u00a0\u00a0\u00a0CodeIgniter\\CodeIgniter->runController()","index":"\u00a0\u00a07\u00a0\u00a0\u00a0\u00a0"},{"file":"SYSTEMPATH\/CodeIgniter.php:355","function":"\u00a0\u00a0\u00a0\u00a0\u00a0\u00a0\u00a0\u00a0CodeIgniter\\CodeIgniter->handleRequest()","index":"\u00a0\u00a08\u00a0\u00a0\u00a0\u00a0"},{"file":"SYSTEMPATH\/Boot.php:312","function":"\u00a0\u00a0\u00a0\u00a0\u00a0\u00a0\u00a0\u00a0CodeIgniter\\CodeIgniter->run()","index":"\u00a0\u00a09\u00a0\u00a0\u00a0\u00a0"},{"file":"SYSTEMPATH\/Boot.php:67","function":"\u00a0\u00a0\u00a0\u00a0\u00a0\u00a0\u00a0\u00a0CodeIgniter\\Boot::runCodeIgniter()","index":"\u00a010\u00a0\u00a0\u00a0\u00a0"},{"file":"FCPATH\/index.php:56","function":"\u00a0\u00a0\u00a0\u00a0\u00a0\u00a0\u00a0\u00a0CodeIgniter\\Boot::bootWeb()","index":"\u00a011\u00a0\u00a0\u00a0\u00a0"}],"trace-file":"APPPATH\/Models\/LotteryModel.php:23","qid":"b09f247cbc9cd1b5dc44e3c885f800e4"},{"hover":"","class":"","duration":"2.62 ms","sql":"<strong>SELECT<\/strong> *\n<strong>FROM<\/strong> `lottery_data`\n<strong>WHERE<\/strong> `type` = &#039;SGPTT&#039;\n<strong>ORDER<\/strong> <strong>BY<\/strong> `id` <strong>DESC<\/strong>\n <strong>LIMIT<\/strong> 1","trace":[{"file":"SYSTEMPATH\/Database\/BaseBuilder.php:1629","function":"\u00a0\u00a0\u00a0\u00a0\u00a0\u00a0\u00a0\u00a0CodeIgniter\\Database\\BaseConnection->query()","index":"\u00a0\u00a01\u00a0\u00a0\u00a0\u00a0"},{"file":"SYSTEMPATH\/Model.php:319","function":"\u00a0\u00a0\u00a0\u00a0\u00a0\u00a0\u00a0\u00a0CodeIgniter\\Database\\BaseBuilder->get()","index":"\u00a0\u00a02\u00a0\u00a0\u00a0\u00a0"},{"file":"SYSTEMPATH\/BaseModel.php:714","function":"\u00a0\u00a0\u00a0\u00a0\u00a0\u00a0\u00a0\u00a0CodeIgniter\\Model->doFirst()","index":"\u00a0\u00a03\u00a0\u00a0\u00a0\u00a0"},{"file":"APPPATH\/Models\/LotteryModel.php:23","function":"\u00a0\u00a0\u00a0\u00a0\u00a0\u00a0\u00a0\u00a0CodeIgniter\\BaseModel->first()","index":"\u00a0\u00a04\u00a0\u00a0\u00a0\u00a0"},{"file":"APPPATH\/Controllers\/LotteryData.php:51","function":"\u00a0\u00a0\u00a0\u00a0\u00a0\u00a0\u00a0\u00a0App\\Models\\LotteryModel->getLotteryDataByType()","index":"\u00a0\u00a05\u00a0\u00a0\u00a0\u00a0"},{"file":"SYSTEMPATH\/CodeIgniter.php:933","function":"\u00a0\u00a0\u00a0\u00a0\u00a0\u00a0\u00a0\u00a0App\\Controllers\\LotteryData->fetchAll()","index":"\u00a0\u00a06\u00a0\u00a0\u00a0\u00a0"},{"file":"SYSTEMPATH\/CodeIgniter.php:509","function":"\u00a0\u00a0\u00a0\u00a0\u00a0\u00a0\u00a0\u00a0CodeIgniter\\CodeIgniter->runController()","index":"\u00a0\u00a07\u00a0\u00a0\u00a0\u00a0"},{"file":"SYSTEMPATH\/CodeIgniter.php:355","function":"\u00a0\u00a0\u00a0\u00a0\u00a0\u00a0\u00a0\u00a0CodeIgniter\\CodeIgniter->handleRequest()","index":"\u00a0\u00a08\u00a0\u00a0\u00a0\u00a0"},{"file":"SYSTEMPATH\/Boot.php:312","function":"\u00a0\u00a0\u00a0\u00a0\u00a0\u00a0\u00a0\u00a0CodeIgniter\\CodeIgniter->run()","index":"\u00a0\u00a09\u00a0\u00a0\u00a0\u00a0"},{"file":"SYSTEMPATH\/Boot.php:67","function":"\u00a0\u00a0\u00a0\u00a0\u00a0\u00a0\u00a0\u00a0CodeIgniter\\Boot::runCodeIgniter()","index":"\u00a010\u00a0\u00a0\u00a0\u00a0"},{"file":"FCPATH\/index.php:56","function":"\u00a0\u00a0\u00a0\u00a0\u00a0\u00a0\u00a0\u00a0CodeIgniter\\Boot::bootWeb()","index":"\u00a011\u00a0\u00a0\u00a0\u00a0"}],"trace-file":"APPPATH\/Models\/LotteryModel.php:23","qid":"9f2b705cd73e1673c2af3f0f547a3209"},{"hover":"","class":"","duration":"3.56 ms","sql":"<strong>SELECT<\/strong> *\n<strong>FROM<\/strong> `lottery_data`\n<strong>WHERE<\/strong> `type` = &#039;M4DJG&#039;\n<strong>ORDER<\/strong> <strong>BY<\/strong> `id` <strong>DESC<\/strong>\n <strong>LIMIT<\/strong> 1","trace":[{"file":"SYSTEMPATH\/Database\/BaseBuilder.php:1629","function":"\u00a0\u00a0\u00a0\u00a0\u00a0\u00a0\u00a0\u00a0CodeIgniter\\Database\\BaseConnection->query()","index":"\u00a0\u00a01\u00a0\u00a0\u00a0\u00a0"},{"file":"SYSTEMPATH\/Model.php:319","function":"\u00a0\u00a0\u00a0\u00a0\u00a0\u00a0\u00a0\u00a0CodeIgniter\\Database\\BaseBuilder->get()","index":"\u00a0\u00a02\u00a0\u00a0\u00a0\u00a0"},{"file":"SYSTEMPATH\/BaseModel.php:714","function":"\u00a0\u00a0\u00a0\u00a0\u00a0\u00a0\u00a0\u00a0CodeIgniter\\Model->doFirst()","index":"\u00a0\u00a03\u00a0\u00a0\u00a0\u00a0"},{"file":"APPPATH\/Models\/LotteryModel.php:23","function":"\u00a0\u00a0\u00a0\u00a0\u00a0\u00a0\u00a0\u00a0CodeIgniter\\BaseModel->first()","index":"\u00a0\u00a04\u00a0\u00a0\u00a0\u00a0"},{"file":"APPPATH\/Controllers\/LotteryData.php:51","function":"\u00a0\u00a0\u00a0\u00a0\u00a0\u00a0\u00a0\u00a0App\\Models\\LotteryModel->getLotteryDataByType()","index":"\u00a0\u00a05\u00a0\u00a0\u00a0\u00a0"},{"file":"SYSTEMPATH\/CodeIgniter.php:933","function":"\u00a0\u00a0\u00a0\u00a0\u00a0\u00a0\u00a0\u00a0App\\Controllers\\LotteryData->fetchAll()","index":"\u00a0\u00a06\u00a0\u00a0\u00a0\u00a0"},{"file":"SYSTEMPATH\/CodeIgniter.php:509","function":"\u00a0\u00a0\u00a0\u00a0\u00a0\u00a0\u00a0\u00a0CodeIgniter\\CodeIgniter->runController()","index":"\u00a0\u00a07\u00a0\u00a0\u00a0\u00a0"},{"file":"SYSTEMPATH\/CodeIgniter.php:355","function":"\u00a0\u00a0\u00a0\u00a0\u00a0\u00a0\u00a0\u00a0CodeIgniter\\CodeIgniter->handleRequest()","index":"\u00a0\u00a08\u00a0\u00a0\u00a0\u00a0"},{"file":"SYSTEMPATH\/Boot.php:312","function":"\u00a0\u00a0\u00a0\u00a0\u00a0\u00a0\u00a0\u00a0CodeIgniter\\CodeIgniter->run()","index":"\u00a0\u00a09\u00a0\u00a0\u00a0\u00a0"},{"file":"SYSTEMPATH\/Boot.php:67","function":"\u00a0\u00a0\u00a0\u00a0\u00a0\u00a0\u00a0\u00a0CodeIgniter\\Boot::runCodeIgniter()","index":"\u00a010\u00a0\u00a0\u00a0\u00a0"},{"file":"FCPATH\/index.php:56","function":"\u00a0\u00a0\u00a0\u00a0\u00a0\u00a0\u00a0\u00a0CodeIgniter\\Boot::bootWeb()","index":"\u00a011\u00a0\u00a0\u00a0\u00a0"}],"trace-file":"APPPATH\/Models\/LotteryModel.php:23","qid":"0ff3a9e421cf07268a8bbe3e0722b22d"},{"hover":"","class":"","duration":"1.59 ms","sql":"<strong>SELECT<\/strong> *\n<strong>FROM<\/strong> `lottery_data`\n<strong>WHERE<\/strong> `type` = &#039;GD&#039;\n<strong>ORDER<\/strong> <strong>BY<\/strong> `id` <strong>DESC<\/strong>\n <strong>LIMIT<\/strong> 1","trace":[{"file":"SYSTEMPATH\/Database\/BaseBuilder.php:1629","function":"\u00a0\u00a0\u00a0\u00a0\u00a0\u00a0\u00a0\u00a0CodeIgniter\\Database\\BaseConnection->query()","index":"\u00a0\u00a01\u00a0\u00a0\u00a0\u00a0"},{"file":"SYSTEMPATH\/Model.php:319","function":"\u00a0\u00a0\u00a0\u00a0\u00a0\u00a0\u00a0\u00a0CodeIgniter\\Database\\BaseBuilder->get()","index":"\u00a0\u00a02\u00a0\u00a0\u00a0\u00a0"},{"file":"SYSTEMPATH\/BaseModel.php:714","function":"\u00a0\u00a0\u00a0\u00a0\u00a0\u00a0\u00a0\u00a0CodeIgniter\\Model->doFirst()","index":"\u00a0\u00a03\u00a0\u00a0\u00a0\u00a0"},{"file":"APPPATH\/Models\/LotteryModel.php:23","function":"\u00a0\u00a0\u00a0\u00a0\u00a0\u00a0\u00a0\u00a0CodeIgniter\\BaseModel->first()","index":"\u00a0\u00a04\u00a0\u00a0\u00a0\u00a0"},{"file":"APPPATH\/Controllers\/LotteryData.php:51","function":"\u00a0\u00a0\u00a0\u00a0\u00a0\u00a0\u00a0\u00a0App\\Models\\LotteryModel->getLotteryDataByType()","index":"\u00a0\u00a05\u00a0\u00a0\u00a0\u00a0"},{"file":"SYSTEMPATH\/CodeIgniter.php:933","function":"\u00a0\u00a0\u00a0\u00a0\u00a0\u00a0\u00a0\u00a0App\\Controllers\\LotteryData->fetchAll()","index":"\u00a0\u00a06\u00a0\u00a0\u00a0\u00a0"},{"file":"SYSTEMPATH\/CodeIgniter.php:509","function":"\u00a0\u00a0\u00a0\u00a0\u00a0\u00a0\u00a0\u00a0CodeIgniter\\CodeIgniter->runController()","index":"\u00a0\u00a07\u00a0\u00a0\u00a0\u00a0"},{"file":"SYSTEMPATH\/CodeIgniter.php:355","function":"\u00a0\u00a0\u00a0\u00a0\u00a0\u00a0\u00a0\u00a0CodeIgniter\\CodeIgniter->handleRequest()","index":"\u00a0\u00a08\u00a0\u00a0\u00a0\u00a0"},{"file":"SYSTEMPATH\/Boot.php:312","function":"\u00a0\u00a0\u00a0\u00a0\u00a0\u00a0\u00a0\u00a0CodeIgniter\\CodeIgniter->run()","index":"\u00a0\u00a09\u00a0\u00a0\u00a0\u00a0"},{"file":"SYSTEMPATH\/Boot.php:67","function":"\u00a0\u00a0\u00a0\u00a0\u00a0\u00a0\u00a0\u00a0CodeIgniter\\Boot::runCodeIgniter()","index":"\u00a010\u00a0\u00a0\u00a0\u00a0"},{"file":"FCPATH\/index.php:56","function":"\u00a0\u00a0\u00a0\u00a0\u00a0\u00a0\u00a0\u00a0CodeIgniter\\Boot::bootWeb()","index":"\u00a011\u00a0\u00a0\u00a0\u00a0"}],"trace-file":"APPPATH\/Models\/LotteryModel.php:23","qid":"c32af8dec27417300d67ffa68fc04a04"},{"hover":"","class":"","duration":"0.46 ms","sql":"<strong>SELECT<\/strong> *\n<strong>FROM<\/strong> `lottery_data`\n<strong>WHERE<\/strong> `type` = &#039;H4D6D1&#039;\n<strong>ORDER<\/strong> <strong>BY<\/strong> `id` <strong>DESC<\/strong>\n <strong>LIMIT<\/strong> 1","trace":[{"file":"SYSTEMPATH\/Database\/BaseBuilder.php:1629","function":"\u00a0\u00a0\u00a0\u00a0\u00a0\u00a0\u00a0\u00a0CodeIgniter\\Database\\BaseConnection->query()","index":"\u00a0\u00a01\u00a0\u00a0\u00a0\u00a0"},{"file":"SYSTEMPATH\/Model.php:319","function":"\u00a0\u00a0\u00a0\u00a0\u00a0\u00a0\u00a0\u00a0CodeIgniter\\Database\\BaseBuilder->get()","index":"\u00a0\u00a02\u00a0\u00a0\u00a0\u00a0"},{"file":"SYSTEMPATH\/BaseModel.php:714","function":"\u00a0\u00a0\u00a0\u00a0\u00a0\u00a0\u00a0\u00a0CodeIgniter\\Model->doFirst()","index":"\u00a0\u00a03\u00a0\u00a0\u00a0\u00a0"},{"file":"APPPATH\/Models\/LotteryModel.php:23","function":"\u00a0\u00a0\u00a0\u00a0\u00a0\u00a0\u00a0\u00a0CodeIgniter\\BaseModel->first()","index":"\u00a0\u00a04\u00a0\u00a0\u00a0\u00a0"},{"file":"APPPATH\/Controllers\/LotteryData.php:51","function":"\u00a0\u00a0\u00a0\u00a0\u00a0\u00a0\u00a0\u00a0App\\Models\\LotteryModel->getLotteryDataByType()","index":"\u00a0\u00a05\u00a0\u00a0\u00a0\u00a0"},{"file":"SYSTEMPATH\/CodeIgniter.php:933","function":"\u00a0\u00a0\u00a0\u00a0\u00a0\u00a0\u00a0\u00a0App\\Controllers\\LotteryData->fetchAll()","index":"\u00a0\u00a06\u00a0\u00a0\u00a0\u00a0"},{"file":"SYSTEMPATH\/CodeIgniter.php:509","function":"\u00a0\u00a0\u00a0\u00a0\u00a0\u00a0\u00a0\u00a0CodeIgniter\\CodeIgniter->runController()","index":"\u00a0\u00a07\u00a0\u00a0\u00a0\u00a0"},{"file":"SYSTEMPATH\/CodeIgniter.php:355","function":"\u00a0\u00a0\u00a0\u00a0\u00a0\u00a0\u00a0\u00a0CodeIgniter\\CodeIgniter->handleRequest()","index":"\u00a0\u00a08\u00a0\u00a0\u00a0\u00a0"},{"file":"SYSTEMPATH\/Boot.php:312","function":"\u00a0\u00a0\u00a0\u00a0\u00a0\u00a0\u00a0\u00a0CodeIgniter\\CodeIgniter->run()","index":"\u00a0\u00a09\u00a0\u00a0\u00a0\u00a0"},{"file":"SYSTEMPATH\/Boot.php:67","function":"\u00a0\u00a0\u00a0\u00a0\u00a0\u00a0\u00a0\u00a0CodeIgniter\\Boot::runCodeIgniter()","index":"\u00a010\u00a0\u00a0\u00a0\u00a0"},{"file":"FCPATH\/index.php:56","function":"\u00a0\u00a0\u00a0\u00a0\u00a0\u00a0\u00a0\u00a0CodeIgniter\\Boot::bootWeb()","index":"\u00a011\u00a0\u00a0\u00a0\u00a0"}],"trace-file":"APPPATH\/Models\/LotteryModel.php:23","qid":"e9978a9a4b9ceae095fbd1baac343b4a"},{"hover":"","class":"","duration":"0.37 ms","sql":"<strong>SELECT<\/strong> *\n<strong>FROM<\/strong> `lottery_data`\n<strong>WHERE<\/strong> `type` = &#039;H4D6D2&#039;\n<strong>ORDER<\/strong> <strong>BY<\/strong> `id` <strong>DESC<\/strong>\n <strong>LIMIT<\/strong> 1","trace":[{"file":"SYSTEMPATH\/Database\/BaseBuilder.php:1629","function":"\u00a0\u00a0\u00a0\u00a0\u00a0\u00a0\u00a0\u00a0CodeIgniter\\Database\\BaseConnection->query()","index":"\u00a0\u00a01\u00a0\u00a0\u00a0\u00a0"},{"file":"SYSTEMPATH\/Model.php:319","function":"\u00a0\u00a0\u00a0\u00a0\u00a0\u00a0\u00a0\u00a0CodeIgniter\\Database\\BaseBuilder->get()","index":"\u00a0\u00a02\u00a0\u00a0\u00a0\u00a0"},{"file":"SYSTEMPATH\/BaseModel.php:714","function":"\u00a0\u00a0\u00a0\u00a0\u00a0\u00a0\u00a0\u00a0CodeIgniter\\Model->doFirst()","index":"\u00a0\u00a03\u00a0\u00a0\u00a0\u00a0"},{"file":"APPPATH\/Models\/LotteryModel.php:23","function":"\u00a0\u00a0\u00a0\u00a0\u00a0\u00a0\u00a0\u00a0CodeIgniter\\BaseModel->first()","index":"\u00a0\u00a04\u00a0\u00a0\u00a0\u00a0"},{"file":"APPPATH\/Controllers\/LotteryData.php:51","function":"\u00a0\u00a0\u00a0\u00a0\u00a0\u00a0\u00a0\u00a0App\\Models\\LotteryModel->getLotteryDataByType()","index":"\u00a0\u00a05\u00a0\u00a0\u00a0\u00a0"},{"file":"SYSTEMPATH\/CodeIgniter.php:933","function":"\u00a0\u00a0\u00a0\u00a0\u00a0\u00a0\u00a0\u00a0App\\Controllers\\LotteryData->fetchAll()","index":"\u00a0\u00a06\u00a0\u00a0\u00a0\u00a0"},{"file":"SYSTEMPATH\/CodeIgniter.php:509","function":"\u00a0\u00a0\u00a0\u00a0\u00a0\u00a0\u00a0\u00a0CodeIgniter\\CodeIgniter->runController()","index":"\u00a0\u00a07\u00a0\u00a0\u00a0\u00a0"},{"file":"SYSTEMPATH\/CodeIgniter.php:355","function":"\u00a0\u00a0\u00a0\u00a0\u00a0\u00a0\u00a0\u00a0CodeIgniter\\CodeIgniter->handleRequest()","index":"\u00a0\u00a08\u00a0\u00a0\u00a0\u00a0"},{"file":"SYSTEMPATH\/Boot.php:312","function":"\u00a0\u00a0\u00a0\u00a0\u00a0\u00a0\u00a0\u00a0CodeIgniter\\CodeIgniter->run()","index":"\u00a0\u00a09\u00a0\u00a0\u00a0\u00a0"},{"file":"SYSTEMPATH\/Boot.php:67","function":"\u00a0\u00a0\u00a0\u00a0\u00a0\u00a0\u00a0\u00a0CodeIgniter\\Boot::runCodeIgniter()","index":"\u00a010\u00a0\u00a0\u00a0\u00a0"},{"file":"FCPATH\/index.php:56","function":"\u00a0\u00a0\u00a0\u00a0\u00a0\u00a0\u00a0\u00a0CodeIgniter\\Boot::bootWeb()","index":"\u00a011\u00a0\u00a0\u00a0\u00a0"}],"trace-file":"APPPATH\/Models\/LotteryModel.php:23","qid":"086db164dac6448864976febc1d3f89c"},{"hover":"","class":"","duration":"0.3 ms","sql":"<strong>SELECT<\/strong> *\n<strong>FROM<\/strong> `lottery_data`\n<strong>WHERE<\/strong> `type` = &#039;P4D2&#039;\n<strong>ORDER<\/strong> <strong>BY<\/strong> `id` <strong>DESC<\/strong>\n <strong>LIMIT<\/strong> 1","trace":[{"file":"SYSTEMPATH\/Database\/BaseBuilder.php:1629","function":"\u00a0\u00a0\u00a0\u00a0\u00a0\u00a0\u00a0\u00a0CodeIgniter\\Database\\BaseConnection->query()","index":"\u00a0\u00a01\u00a0\u00a0\u00a0\u00a0"},{"file":"SYSTEMPATH\/Model.php:319","function":"\u00a0\u00a0\u00a0\u00a0\u00a0\u00a0\u00a0\u00a0CodeIgniter\\Database\\BaseBuilder->get()","index":"\u00a0\u00a02\u00a0\u00a0\u00a0\u00a0"},{"file":"SYSTEMPATH\/BaseModel.php:714","function":"\u00a0\u00a0\u00a0\u00a0\u00a0\u00a0\u00a0\u00a0CodeIgniter\\Model->doFirst()","index":"\u00a0\u00a03\u00a0\u00a0\u00a0\u00a0"},{"file":"APPPATH\/Models\/LotteryModel.php:23","function":"\u00a0\u00a0\u00a0\u00a0\u00a0\u00a0\u00a0\u00a0CodeIgniter\\BaseModel->first()","index":"\u00a0\u00a04\u00a0\u00a0\u00a0\u00a0"},{"file":"APPPATH\/Controllers\/LotteryData.php:51","function":"\u00a0\u00a0\u00a0\u00a0\u00a0\u00a0\u00a0\u00a0App\\Models\\LotteryModel->getLotteryDataByType()","index":"\u00a0\u00a05\u00a0\u00a0\u00a0\u00a0"},{"file":"SYSTEMPATH\/CodeIgniter.php:933","function":"\u00a0\u00a0\u00a0\u00a0\u00a0\u00a0\u00a0\u00a0App\\Controllers\\LotteryData->fetchAll()","index":"\u00a0\u00a06\u00a0\u00a0\u00a0\u00a0"},{"file":"SYSTEMPATH\/CodeIgniter.php:509","function":"\u00a0\u00a0\u00a0\u00a0\u00a0\u00a0\u00a0\u00a0CodeIgniter\\CodeIgniter->runController()","index":"\u00a0\u00a07\u00a0\u00a0\u00a0\u00a0"},{"file":"SYSTEMPATH\/CodeIgniter.php:355","function":"\u00a0\u00a0\u00a0\u00a0\u00a0\u00a0\u00a0\u00a0CodeIgniter\\CodeIgniter->handleRequest()","index":"\u00a0\u00a08\u00a0\u00a0\u00a0\u00a0"},{"file":"SYSTEMPATH\/Boot.php:312","function":"\u00a0\u00a0\u00a0\u00a0\u00a0\u00a0\u00a0\u00a0CodeIgniter\\CodeIgniter->run()","index":"\u00a0\u00a09\u00a0\u00a0\u00a0\u00a0"},{"file":"SYSTEMPATH\/Boot.php:67","function":"\u00a0\u00a0\u00a0\u00a0\u00a0\u00a0\u00a0\u00a0CodeIgniter\\Boot::runCodeIgniter()","index":"\u00a010\u00a0\u00a0\u00a0\u00a0"},{"file":"FCPATH\/index.php:56","function":"\u00a0\u00a0\u00a0\u00a0\u00a0\u00a0\u00a0\u00a0CodeIgniter\\Boot::bootWeb()","index":"\u00a011\u00a0\u00a0\u00a0\u00a0"}],"trace-file":"APPPATH\/Models\/LotteryModel.php:23","qid":"92a271cd163a1f71735f54e22c4b1a2a"},{"hover":"","class":"","duration":"0.29 ms","sql":"<strong>SELECT<\/strong> *\n<strong>FROM<\/strong> `lottery_data`\n<strong>WHERE<\/strong> `type` = &#039;P4D1&#039;\n<strong>ORDER<\/strong> <strong>BY<\/strong> `id` <strong>DESC<\/strong>\n <strong>LIMIT<\/strong> 1","trace":[{"file":"SYSTEMPATH\/Database\/BaseBuilder.php:1629","function":"\u00a0\u00a0\u00a0\u00a0\u00a0\u00a0\u00a0\u00a0CodeIgniter\\Database\\BaseConnection->query()","index":"\u00a0\u00a01\u00a0\u00a0\u00a0\u00a0"},{"file":"SYSTEMPATH\/Model.php:319","function":"\u00a0\u00a0\u00a0\u00a0\u00a0\u00a0\u00a0\u00a0CodeIgniter\\Database\\BaseBuilder->get()","index":"\u00a0\u00a02\u00a0\u00a0\u00a0\u00a0"},{"file":"SYSTEMPATH\/BaseModel.php:714","function":"\u00a0\u00a0\u00a0\u00a0\u00a0\u00a0\u00a0\u00a0CodeIgniter\\Model->doFirst()","index":"\u00a0\u00a03\u00a0\u00a0\u00a0\u00a0"},{"file":"APPPATH\/Models\/LotteryModel.php:23","function":"\u00a0\u00a0\u00a0\u00a0\u00a0\u00a0\u00a0\u00a0CodeIgniter\\BaseModel->first()","index":"\u00a0\u00a04\u00a0\u00a0\u00a0\u00a0"},{"file":"APPPATH\/Controllers\/LotteryData.php:51","function":"\u00a0\u00a0\u00a0\u00a0\u00a0\u00a0\u00a0\u00a0App\\Models\\LotteryModel->getLotteryDataByType()","index":"\u00a0\u00a05\u00a0\u00a0\u00a0\u00a0"},{"file":"SYSTEMPATH\/CodeIgniter.php:933","function":"\u00a0\u00a0\u00a0\u00a0\u00a0\u00a0\u00a0\u00a0App\\Controllers\\LotteryData->fetchAll()","index":"\u00a0\u00a06\u00a0\u00a0\u00a0\u00a0"},{"file":"SYSTEMPATH\/CodeIgniter.php:509","function":"\u00a0\u00a0\u00a0\u00a0\u00a0\u00a0\u00a0\u00a0CodeIgniter\\CodeIgniter->runController()","index":"\u00a0\u00a07\u00a0\u00a0\u00a0\u00a0"},{"file":"SYSTEMPATH\/CodeIgniter.php:355","function":"\u00a0\u00a0\u00a0\u00a0\u00a0\u00a0\u00a0\u00a0CodeIgniter\\CodeIgniter->handleRequest()","index":"\u00a0\u00a08\u00a0\u00a0\u00a0\u00a0"},{"file":"SYSTEMPATH\/Boot.php:312","function":"\u00a0\u00a0\u00a0\u00a0\u00a0\u00a0\u00a0\u00a0CodeIgniter\\CodeIgniter->run()","index":"\u00a0\u00a09\u00a0\u00a0\u00a0\u00a0"},{"file":"SYSTEMPATH\/Boot.php:67","function":"\u00a0\u00a0\u00a0\u00a0\u00a0\u00a0\u00a0\u00a0CodeIgniter\\Boot::runCodeIgniter()","index":"\u00a010\u00a0\u00a0\u00a0\u00a0"},{"file":"FCPATH\/index.php:56","function":"\u00a0\u00a0\u00a0\u00a0\u00a0\u00a0\u00a0\u00a0CodeIgniter\\Boot::bootWeb()","index":"\u00a011\u00a0\u00a0\u00a0\u00a0"}],"trace-file":"APPPATH\/Models\/LotteryModel.php:23","qid":"0d0bb4cad8a9fba367ff5c9872187ebc"},{"hover":"","class":"","duration":"5.85 ms","sql":"<strong>SELECT<\/strong> *\n<strong>FROM<\/strong> `lottery_data`\n<strong>WHERE<\/strong> `type` = &#039;LMC&#039;\n<strong>ORDER<\/strong> <strong>BY<\/strong> `id` <strong>DESC<\/strong>\n <strong>LIMIT<\/strong> 1","trace":[{"file":"SYSTEMPATH\/Database\/BaseBuilder.php:1629","function":"\u00a0\u00a0\u00a0\u00a0\u00a0\u00a0\u00a0\u00a0CodeIgniter\\Database\\BaseConnection->query()","index":"\u00a0\u00a01\u00a0\u00a0\u00a0\u00a0"},{"file":"SYSTEMPATH\/Model.php:319","function":"\u00a0\u00a0\u00a0\u00a0\u00a0\u00a0\u00a0\u00a0CodeIgniter\\Database\\BaseBuilder->get()","index":"\u00a0\u00a02\u00a0\u00a0\u00a0\u00a0"},{"file":"SYSTEMPATH\/BaseModel.php:714","function":"\u00a0\u00a0\u00a0\u00a0\u00a0\u00a0\u00a0\u00a0CodeIgniter\\Model->doFirst()","index":"\u00a0\u00a03\u00a0\u00a0\u00a0\u00a0"},{"file":"APPPATH\/Models\/LotteryModel.php:23","function":"\u00a0\u00a0\u00a0\u00a0\u00a0\u00a0\u00a0\u00a0CodeIgniter\\BaseModel->first()","index":"\u00a0\u00a04\u00a0\u00a0\u00a0\u00a0"},{"file":"APPPATH\/Controllers\/LotteryData.php:51","function":"\u00a0\u00a0\u00a0\u00a0\u00a0\u00a0\u00a0\u00a0App\\Models\\LotteryModel->getLotteryDataByType()","index":"\u00a0\u00a05\u00a0\u00a0\u00a0\u00a0"},{"file":"SYSTEMPATH\/CodeIgniter.php:933","function":"\u00a0\u00a0\u00a0\u00a0\u00a0\u00a0\u00a0\u00a0App\\Controllers\\LotteryData->fetchAll()","index":"\u00a0\u00a06\u00a0\u00a0\u00a0\u00a0"},{"file":"SYSTEMPATH\/CodeIgniter.php:509","function":"\u00a0\u00a0\u00a0\u00a0\u00a0\u00a0\u00a0\u00a0CodeIgniter\\CodeIgniter->runController()","index":"\u00a0\u00a07\u00a0\u00a0\u00a0\u00a0"},{"file":"SYSTEMPATH\/CodeIgniter.php:355","function":"\u00a0\u00a0\u00a0\u00a0\u00a0\u00a0\u00a0\u00a0CodeIgniter\\CodeIgniter->handleRequest()","index":"\u00a0\u00a08\u00a0\u00a0\u00a0\u00a0"},{"file":"SYSTEMPATH\/Boot.php:312","function":"\u00a0\u00a0\u00a0\u00a0\u00a0\u00a0\u00a0\u00a0CodeIgniter\\CodeIgniter->run()","index":"\u00a0\u00a09\u00a0\u00a0\u00a0\u00a0"},{"file":"SYSTEMPATH\/Boot.php:67","function":"\u00a0\u00a0\u00a0\u00a0\u00a0\u00a0\u00a0\u00a0CodeIgniter\\Boot::runCodeIgniter()","index":"\u00a010\u00a0\u00a0\u00a0\u00a0"},{"file":"FCPATH\/index.php:56","function":"\u00a0\u00a0\u00a0\u00a0\u00a0\u00a0\u00a0\u00a0CodeIgniter\\Boot::bootWeb()","index":"\u00a011\u00a0\u00a0\u00a0\u00a0"}],"trace-file":"APPPATH\/Models\/LotteryModel.php:23","qid":"0be5011a0e97d72809db5d27d6cec300"},{"hover":"","class":"","duration":"27.5 ms","sql":"<strong>SELECT<\/strong> *\n<strong>FROM<\/strong> `lottery_data`\n<strong>WHERE<\/strong> `type` = &#039;LMC1&#039;\n<strong>ORDER<\/strong> <strong>BY<\/strong> `id` <strong>DESC<\/strong>\n <strong>LIMIT<\/strong> 1","trace":[{"file":"SYSTEMPATH\/Database\/BaseBuilder.php:1629","function":"\u00a0\u00a0\u00a0\u00a0\u00a0\u00a0\u00a0\u00a0CodeIgniter\\Database\\BaseConnection->query()","index":"\u00a0\u00a01\u00a0\u00a0\u00a0\u00a0"},{"file":"SYSTEMPATH\/Model.php:319","function":"\u00a0\u00a0\u00a0\u00a0\u00a0\u00a0\u00a0\u00a0CodeIgniter\\Database\\BaseBuilder->get()","index":"\u00a0\u00a02\u00a0\u00a0\u00a0\u00a0"},{"file":"SYSTEMPATH\/BaseModel.php:714","function":"\u00a0\u00a0\u00a0\u00a0\u00a0\u00a0\u00a0\u00a0CodeIgniter\\Model->doFirst()","index":"\u00a0\u00a03\u00a0\u00a0\u00a0\u00a0"},{"file":"APPPATH\/Models\/LotteryModel.php:23","function":"\u00a0\u00a0\u00a0\u00a0\u00a0\u00a0\u00a0\u00a0CodeIgniter\\BaseModel->first()","index":"\u00a0\u00a04\u00a0\u00a0\u00a0\u00a0"},{"file":"APPPATH\/Controllers\/LotteryData.php:51","function":"\u00a0\u00a0\u00a0\u00a0\u00a0\u00a0\u00a0\u00a0App\\Models\\LotteryModel->getLotteryDataByType()","index":"\u00a0\u00a05\u00a0\u00a0\u00a0\u00a0"},{"file":"SYSTEMPATH\/CodeIgniter.php:933","function":"\u00a0\u00a0\u00a0\u00a0\u00a0\u00a0\u00a0\u00a0App\\Controllers\\LotteryData->fetchAll()","index":"\u00a0\u00a06\u00a0\u00a0\u00a0\u00a0"},{"file":"SYSTEMPATH\/CodeIgniter.php:509","function":"\u00a0\u00a0\u00a0\u00a0\u00a0\u00a0\u00a0\u00a0CodeIgniter\\CodeIgniter->runController()","index":"\u00a0\u00a07\u00a0\u00a0\u00a0\u00a0"},{"file":"SYSTEMPATH\/CodeIgniter.php:355","function":"\u00a0\u00a0\u00a0\u00a0\u00a0\u00a0\u00a0\u00a0CodeIgniter\\CodeIgniter->handleRequest()","index":"\u00a0\u00a08\u00a0\u00a0\u00a0\u00a0"},{"file":"SYSTEMPATH\/Boot.php:312","function":"\u00a0\u00a0\u00a0\u00a0\u00a0\u00a0\u00a0\u00a0CodeIgniter\\CodeIgniter->run()","index":"\u00a0\u00a09\u00a0\u00a0\u00a0\u00a0"},{"file":"SYSTEMPATH\/Boot.php:67","function":"\u00a0\u00a0\u00a0\u00a0\u00a0\u00a0\u00a0\u00a0CodeIgniter\\Boot::runCodeIgniter()","index":"\u00a010\u00a0\u00a0\u00a0\u00a0"},{"file":"FCPATH\/index.php:56","function":"\u00a0\u00a0\u00a0\u00a0\u00a0\u00a0\u00a0\u00a0CodeIgniter\\Boot::bootWeb()","index":"\u00a011\u00a0\u00a0\u00a0\u00a0"}],"trace-file":"APPPATH\/Models\/LotteryModel.php:23","qid":"cc65d6b02898d65b0e305f99ee6ca995"},{"hover":"","class":"","duration":"3.93 ms","sql":"<strong>SELECT<\/strong> *\n<strong>FROM<\/strong> `lottery_data`\n<strong>WHERE<\/strong> `type` = &#039;MTH&#039;\n<strong>ORDER<\/strong> <strong>BY<\/strong> `id` <strong>DESC<\/strong>\n <strong>LIMIT<\/strong> 1","trace":[{"file":"SYSTEMPATH\/Database\/BaseBuilder.php:1629","function":"\u00a0\u00a0\u00a0\u00a0\u00a0\u00a0\u00a0\u00a0CodeIgniter\\Database\\BaseConnection->query()","index":"\u00a0\u00a01\u00a0\u00a0\u00a0\u00a0"},{"file":"SYSTEMPATH\/Model.php:319","function":"\u00a0\u00a0\u00a0\u00a0\u00a0\u00a0\u00a0\u00a0CodeIgniter\\Database\\BaseBuilder->get()","index":"\u00a0\u00a02\u00a0\u00a0\u00a0\u00a0"},{"file":"SYSTEMPATH\/BaseModel.php:714","function":"\u00a0\u00a0\u00a0\u00a0\u00a0\u00a0\u00a0\u00a0CodeIgniter\\Model->doFirst()","index":"\u00a0\u00a03\u00a0\u00a0\u00a0\u00a0"},{"file":"APPPATH\/Models\/LotteryModel.php:23","function":"\u00a0\u00a0\u00a0\u00a0\u00a0\u00a0\u00a0\u00a0CodeIgniter\\BaseModel->first()","index":"\u00a0\u00a04\u00a0\u00a0\u00a0\u00a0"},{"file":"APPPATH\/Controllers\/LotteryData.php:51","function":"\u00a0\u00a0\u00a0\u00a0\u00a0\u00a0\u00a0\u00a0App\\Models\\LotteryModel->getLotteryDataByType()","index":"\u00a0\u00a05\u00a0\u00a0\u00a0\u00a0"},{"file":"SYSTEMPATH\/CodeIgniter.php:933","function":"\u00a0\u00a0\u00a0\u00a0\u00a0\u00a0\u00a0\u00a0App\\Controllers\\LotteryData->fetchAll()","index":"\u00a0\u00a06\u00a0\u00a0\u00a0\u00a0"},{"file":"SYSTEMPATH\/CodeIgniter.php:509","function":"\u00a0\u00a0\u00a0\u00a0\u00a0\u00a0\u00a0\u00a0CodeIgniter\\CodeIgniter->runController()","index":"\u00a0\u00a07\u00a0\u00a0\u00a0\u00a0"},{"file":"SYSTEMPATH\/CodeIgniter.php:355","function":"\u00a0\u00a0\u00a0\u00a0\u00a0\u00a0\u00a0\u00a0CodeIgniter\\CodeIgniter->handleRequest()","index":"\u00a0\u00a08\u00a0\u00a0\u00a0\u00a0"},{"file":"SYSTEMPATH\/Boot.php:312","function":"\u00a0\u00a0\u00a0\u00a0\u00a0\u00a0\u00a0\u00a0CodeIgniter\\CodeIgniter->run()","index":"\u00a0\u00a09\u00a0\u00a0\u00a0\u00a0"},{"file":"SYSTEMPATH\/Boot.php:67","function":"\u00a0\u00a0\u00a0\u00a0\u00a0\u00a0\u00a0\u00a0CodeIgniter\\Boot::runCodeIgniter()","index":"\u00a010\u00a0\u00a0\u00a0\u00a0"},{"file":"FCPATH\/index.php:56","function":"\u00a0\u00a0\u00a0\u00a0\u00a0\u00a0\u00a0\u00a0CodeIgniter\\Boot::bootWeb()","index":"\u00a011\u00a0\u00a0\u00a0\u00a0"}],"trace-file":"APPPATH\/Models\/LotteryModel.php:23","qid":"c6e38776f3b529f4fbf610a0da8a9211"},{"hover":"","class":"","duration":"0.56 ms","sql":"<strong>SELECT<\/strong> *\n<strong>FROM<\/strong> `lottery_data`\n<strong>WHERE<\/strong> `type` = &#039;NLT&#039;\n<strong>ORDER<\/strong> <strong>BY<\/strong> `id` <strong>DESC<\/strong>\n <strong>LIMIT<\/strong> 1","trace":[{"file":"SYSTEMPATH\/Database\/BaseBuilder.php:1629","function":"\u00a0\u00a0\u00a0\u00a0\u00a0\u00a0\u00a0\u00a0CodeIgniter\\Database\\BaseConnection->query()","index":"\u00a0\u00a01\u00a0\u00a0\u00a0\u00a0"},{"file":"SYSTEMPATH\/Model.php:319","function":"\u00a0\u00a0\u00a0\u00a0\u00a0\u00a0\u00a0\u00a0CodeIgniter\\Database\\BaseBuilder->get()","index":"\u00a0\u00a02\u00a0\u00a0\u00a0\u00a0"},{"file":"SYSTEMPATH\/BaseModel.php:714","function":"\u00a0\u00a0\u00a0\u00a0\u00a0\u00a0\u00a0\u00a0CodeIgniter\\Model->doFirst()","index":"\u00a0\u00a03\u00a0\u00a0\u00a0\u00a0"},{"file":"APPPATH\/Models\/LotteryModel.php:23","function":"\u00a0\u00a0\u00a0\u00a0\u00a0\u00a0\u00a0\u00a0CodeIgniter\\BaseModel->first()","index":"\u00a0\u00a04\u00a0\u00a0\u00a0\u00a0"},{"file":"APPPATH\/Controllers\/LotteryData.php:51","function":"\u00a0\u00a0\u00a0\u00a0\u00a0\u00a0\u00a0\u00a0App\\Models\\LotteryModel->getLotteryDataByType()","index":"\u00a0\u00a05\u00a0\u00a0\u00a0\u00a0"},{"file":"SYSTEMPATH\/CodeIgniter.php:933","function":"\u00a0\u00a0\u00a0\u00a0\u00a0\u00a0\u00a0\u00a0App\\Controllers\\LotteryData->fetchAll()","index":"\u00a0\u00a06\u00a0\u00a0\u00a0\u00a0"},{"file":"SYSTEMPATH\/CodeIgniter.php:509","function":"\u00a0\u00a0\u00a0\u00a0\u00a0\u00a0\u00a0\u00a0CodeIgniter\\CodeIgniter->runController()","index":"\u00a0\u00a07\u00a0\u00a0\u00a0\u00a0"},{"file":"SYSTEMPATH\/CodeIgniter.php:355","function":"\u00a0\u00a0\u00a0\u00a0\u00a0\u00a0\u00a0\u00a0CodeIgniter\\CodeIgniter->handleRequest()","index":"\u00a0\u00a08\u00a0\u00a0\u00a0\u00a0"},{"file":"SYSTEMPATH\/Boot.php:312","function":"\u00a0\u00a0\u00a0\u00a0\u00a0\u00a0\u00a0\u00a0CodeIgniter\\CodeIgniter->run()","index":"\u00a0\u00a09\u00a0\u00a0\u00a0\u00a0"},{"file":"SYSTEMPATH\/Boot.php:67","function":"\u00a0\u00a0\u00a0\u00a0\u00a0\u00a0\u00a0\u00a0CodeIgniter\\Boot::runCodeIgniter()","index":"\u00a010\u00a0\u00a0\u00a0\u00a0"},{"file":"FCPATH\/index.php:56","function":"\u00a0\u00a0\u00a0\u00a0\u00a0\u00a0\u00a0\u00a0CodeIgniter\\Boot::bootWeb()","index":"\u00a011\u00a0\u00a0\u00a0\u00a0"}],"trace-file":"APPPATH\/Models\/LotteryModel.php:23","qid":"0f497e1d1458b74061881d7639f7ce69"}]},"badgeValue":20,"isEmpty":false,"hasTabContent":true,"hasLabel":false,"icon":"data:image\/png;base64,iVBORw0KGgoAAAANSUhEUgAAABgAAAAYCAYAAADgdz34AAAAAXNSR0IArs4c6QAAAARnQU1BAACxjwv8YQUAAAAJcEhZcwAADsMAAA7DAcdvqGQAAADMSURBVEhLY6A3YExLSwsA4nIycQDIDIhRWEBqamo\/UNF\/SjDQjF6ocZgAKPkRiFeEhoYyQ4WIBiA9QAuWAPEHqBAmgLqgHcolGQD1V4DMgHIxwbCxYD+QBqcKINseKo6eWrBioPrtQBq\/BcgY5ht0cUIYbBg2AJKkRxCNWkDQgtFUNJwtABr+F6igE8olGQD114HMgHIxAVDyAhA\/AlpSA8RYUwoeXAPVex5qHCbIyMgwBCkAuQJIY00huDBUz\/mUlBQDqHGjgBjAwAAACexpph6oHSQAAAAASUVORK5CYII=","hasTimelineData":true,"timelineData":[{"name":"Connecting to Database: \"default\"","component":"Database","start":1760363906.392668,"duration":"0.007213"},{"name":"Query","component":"Database","start":1760363906.399931,"duration":"0.000565","query":"<strong>SELECT<\/strong> *\n<strong>FROM<\/strong> `lottery_data`\n<strong>WHERE<\/strong> `type` = &#039;M4D&#039;\n<strong>ORDER<\/strong> <strong>BY<\/strong> `id` <strong>DESC<\/strong>\n <strong>LIMIT<\/strong> 1"},{"name":"Query","component":"Database","start":1760363906.400936,"duration":"0.000506","query":"<strong>SELECT<\/strong> *\n<strong>FROM<\/strong> `lottery_data`\n<strong>WHERE<\/strong> `type` = &#039;DMC4D&#039;\n<strong>ORDER<\/strong> <strong>BY<\/strong> `id` <strong>DESC<\/strong>\n <strong>LIMIT<\/strong> 1"},{"name":"Query","component":"Database","start":1760363906.401651,"duration":"0.000470","query":"<strong>SELECT<\/strong> *\n<strong>FROM<\/strong> `lottery_data`\n<strong>WHERE<\/strong> `type` = &#039;DMC6D&#039;\n<strong>ORDER<\/strong> <strong>BY<\/strong> `id` <strong>DESC<\/strong>\n <strong>LIMIT<\/strong> 1"},{"name":"Query","component":"Database","start":1760363906.402296,"duration":"0.001170","query":"<strong>SELECT<\/strong> *\n<strong>FROM<\/strong> `lottery_data`\n<strong>WHERE<\/strong> `type` = &#039;TT&#039;\n<strong>ORDER<\/strong> <strong>BY<\/strong> `id` <strong>DESC<\/strong>\n <strong>LIMIT<\/strong> 1"},{"name":"Query","component":"Database","start":1760363906.403649,"duration":"0.000436","query":"<strong>SELECT<\/strong> *\n<strong>FROM<\/strong> `lottery_data`\n<strong>WHERE<\/strong> `type` = &#039;STC&#039;\n<strong>ORDER<\/strong> <strong>BY<\/strong> `id` <strong>DESC<\/strong>\n <strong>LIMIT<\/strong> 1"},{"name":"Query","component":"Database","start":1760363906.404203,"duration":"0.000341","query":"<strong>SELECT<\/strong> *\n<strong>FROM<\/strong> `lottery_data`\n<strong>WHERE<\/strong> `type` = &#039;SB&#039;\n<strong>ORDER<\/strong> <strong>BY<\/strong> `id` <strong>DESC<\/strong>\n <strong>LIMIT<\/strong> 1"},{"name":"Query","component":"Database","start":1760363906.404663,"duration":"0.005245","query":"<strong>SELECT<\/strong> *\n<strong>FROM<\/strong> `lottery_data`\n<strong>WHERE<\/strong> `type` = &#039;SBLT&#039;\n<strong>ORDER<\/strong> <strong>BY<\/strong> `id` <strong>DESC<\/strong>\n <strong>LIMIT<\/strong> 1"},{"name":"Query","component":"Database","start":1760363906.410184,"duration":"0.000561","query":"<strong>SELECT<\/strong> *\n<strong>FROM<\/strong> `lottery_data`\n<strong>WHERE<\/strong> `type` = &#039;SCS&#039;\n<strong>ORDER<\/strong> <strong>BY<\/strong> `id` <strong>DESC<\/strong>\n <strong>LIMIT<\/strong> 1"},{"name":"Query","component":"Database","start":1760363906.411004,"duration":"0.002036","query":"<strong>SELECT<\/strong> *\n<strong>FROM<\/strong> `lottery_data`\n<strong>WHERE<\/strong> `type` = &#039;SGP4D&#039;\n<strong>ORDER<\/strong> <strong>BY<\/strong> `id` <strong>DESC<\/strong>\n <strong>LIMIT<\/strong> 1"},{"name":"Query","component":"Database","start":1760363906.414163,"duration":"0.002620","query":"<strong>SELECT<\/strong> *\n<strong>FROM<\/strong> `lottery_data`\n<strong>WHERE<\/strong> `type` = &#039;SGPTT&#039;\n<strong>ORDER<\/strong> <strong>BY<\/strong> `id` <strong>DESC<\/strong>\n <strong>LIMIT<\/strong> 1"},{"name":"Query","component":"Database","start":1760363906.417048,"duration":"0.003559","query":"<strong>SELECT<\/strong> *\n<strong>FROM<\/strong> `lottery_data`\n<strong>WHERE<\/strong> `type` = &#039;M4DJG&#039;\n<strong>ORDER<\/strong> <strong>BY<\/strong> `id` <strong>DESC<\/strong>\n <strong>LIMIT<\/strong> 1"},{"name":"Query","component":"Database","start":1760363906.420875,"duration":"0.001592","query":"<strong>SELECT<\/strong> *\n<strong>FROM<\/strong> `lottery_data`\n<strong>WHERE<\/strong> `type` = &#039;GD&#039;\n<strong>ORDER<\/strong> <strong>BY<\/strong> `id` <strong>DESC<\/strong>\n <strong>LIMIT<\/strong> 1"},{"name":"Query","component":"Database","start":1760363906.422723,"duration":"0.000456","query":"<strong>SELECT<\/strong> *\n<strong>FROM<\/strong> `lottery_data`\n<strong>WHERE<\/strong> `type` = &#039;H4D6D1&#039;\n<strong>ORDER<\/strong> <strong>BY<\/strong> `id` <strong>DESC<\/strong>\n <strong>LIMIT<\/strong> 1"},{"name":"Query","component":"Database","start":1760363906.423367,"duration":"0.000374","query":"<strong>SELECT<\/strong> *\n<strong>FROM<\/strong> `lottery_data`\n<strong>WHERE<\/strong> `type` = &#039;H4D6D2&#039;\n<strong>ORDER<\/strong> <strong>BY<\/strong> `id` <strong>DESC<\/strong>\n <strong>LIMIT<\/strong> 1"},{"name":"Query","component":"Database","start":1760363906.423899,"duration":"0.000295","query":"<strong>SELECT<\/strong> *\n<strong>FROM<\/strong> `lottery_data`\n<strong>WHERE<\/strong> `type` = &#039;P4D2&#039;\n<strong>ORDER<\/strong> <strong>BY<\/strong> `id` <strong>DESC<\/strong>\n <strong>LIMIT<\/strong> 1"},{"name":"Query","component":"Database","start":1760363906.424318,"duration":"0.000289","query":"<strong>SELECT<\/strong> *\n<strong>FROM<\/strong> `lottery_data`\n<strong>WHERE<\/strong> `type` = &#039;P4D1&#039;\n<strong>ORDER<\/strong> <strong>BY<\/strong> `id` <strong>DESC<\/strong>\n <strong>LIMIT<\/strong> 1"},{"name":"Query","component":"Database","start":1760363906.424762,"duration":"0.005853","query":"<strong>SELECT<\/strong> *\n<strong>FROM<\/strong> `lottery_data`\n<strong>WHERE<\/strong> `type` = &#039;LMC&#039;\n<strong>ORDER<\/strong> <strong>BY<\/strong> `id` <strong>DESC<\/strong>\n <strong>LIMIT<\/strong> 1"},{"name":"Query","component":"Database","start":1760363906.430908,"duration":"0.027501","query":"<strong>SELECT<\/strong> *\n<strong>FROM<\/strong> `lottery_data`\n<strong>WHERE<\/strong> `type` = &#039;LMC1&#039;\n<strong>ORDER<\/strong> <strong>BY<\/strong> `id` <strong>DESC<\/strong>\n <strong>LIMIT<\/strong> 1"},{"name":"Query","component":"Database","start":1760363906.458673,"duration":"0.003928","query":"<strong>SELECT<\/strong> *\n<strong>FROM<\/strong> `lottery_data`\n<strong>WHERE<\/strong> `type` = &#039;MTH&#039;\n<strong>ORDER<\/strong> <strong>BY<\/strong> `id` <strong>DESC<\/strong>\n <strong>LIMIT<\/strong> 1"},{"name":"Query","component":"Database","start":1760363906.462905,"duration":"0.000556","query":"<strong>SELECT<\/strong> *\n<strong>FROM<\/strong> `lottery_data`\n<strong>WHERE<\/strong> `type` = &#039;NLT&#039;\n<strong>ORDER<\/strong> <strong>BY<\/strong> `id` <strong>DESC<\/strong>\n <strong>LIMIT<\/strong> 1"}]},{"title":"Logs","titleSafe":"logs","titleDetails":"","display":{"logs":[{"level":"warning","msg":"[DEPRECATED] Creation of dynamic property App\\Controllers\\LotteryData::$settingModel is deprecated in APPPATH\/Controllers\/LotteryData.php on line 14.\n 1 SYSTEMPATH\/CodeIgniter.php(903): App\\Controllers\\LotteryData->__construct()\n 2 SYSTEMPATH\/CodeIgniter.php(500): CodeIgniter\\CodeIgniter->createController()\n 3 SYSTEMPATH\/CodeIgniter.php(355): CodeIgniter\\CodeIgniter->handleRequest(null, Object(Config\\Cache), false)\n 4 SYSTEMPATH\/Boot.php(312): CodeIgniter\\CodeIgniter->run()\n 5 SYSTEMPATH\/Boot.php(67): CodeIgniter\\Boot::runCodeIgniter(Object(CodeIgniter\\CodeIgniter))\n 6 FCPATH\/index.php(56): CodeIgniter\\Boot::bootWeb(Object(Config\\Paths))"}]},"badgeValue":null,"isEmpty":false,"hasTabContent":true,"hasLabel":false,"icon":"data:image\/png;base64,iVBORw0KGgoAAAANSUhEUgAAABgAAAAYCAYAAADgdz34AAAAAXNSR0IArs4c6QAAAARnQU1BAACxjwv8YQUAAAAJcEhZcwAADsMAAA7DAcdvqGQAAACYSURBVEhLYxgFJIHU1FSjtLS0i0D8AYj7gEKMEBkqAaAFF4D4ERCvAFrwH4gDoFIMKSkpFkB+OTEYqgUTACXfA\/GqjIwMQyD9H2hRHlQKJFcBEiMGQ7VgAqCBvUgK32dmZspCpagGGNPT0\/1BLqeF4bQHQJePpiIwhmrBBEADR1MRfgB0+WgqAmOoFkwANHA0FY0CUgEDAwCQ0PUpNB3kqwAAAABJRU5ErkJggg==","hasTimelineData":false,"timelineData":[]},{"title":"Views","titleSafe":"views","titleDetails":"","display":[],"badgeValue":0,"isEmpty":false,"hasTabContent":false,"hasLabel":true,"icon":"data:image\/png;base64,iVBORw0KGgoAAAANSUhEUgAAABgAAAAYCAYAAADgdz34AAAAAXNSR0IArs4c6QAAAARnQU1BAACxjwv8YQUAAAAJcEhZcwAADsMAAA7DAcdvqGQAAADeSURBVEhL7ZSxDcIwEEWNYA0YgGmgyAaJLTcUaaBzQQEVjMEabBQxAdw53zTHiThEovGTfnE\/9rsoRUxhKLOmaa6Uh7X2+UvguLCzVxN1XW9x4EYHzik033Hp3X0LO+DaQG8MDQcuq6qao4qkHuMgQggLvkPLjqh00ZgFDBacMJYFkuwFlH1mshdkZ5JPJERA9JpI6xNCBESvibQ+IURA9JpI6xNCBESvibQ+IURA9DTsuHTOrVFFxixgB\/eUFlU8uKJ0eDBFOu\/9EvoeKnlJS2\/08Tc8NOwQ8sIfMeYFjqKDjdU2sp4AAAAASUVORK5CYII=","hasTimelineData":true,"timelineData":[]},{"title":"Files","titleSafe":"files","titleDetails":"( 192 )","display":{"coreFiles":[{"path":"SYSTEMPATH\/API\/ResponseTrait.php","name":"ResponseTrait.php"},{"path":"SYSTEMPATH\/Autoloader\/Autoloader.php","name":"Autoloader.php"},{"path":"SYSTEMPATH\/Autoloader\/FileLocator.php","name":"FileLocator.php"},{"path":"SYSTEMPATH\/Autoloader\/FileLocatorInterface.php","name":"FileLocatorInterface.php"},{"path":"SYSTEMPATH\/BaseModel.php","name":"BaseModel.php"},{"path":"SYSTEMPATH\/Boot.php","name":"Boot.php"},{"path":"SYSTEMPATH\/Cache\/CacheFactory.php","name":"CacheFactory.php"},{"path":"SYSTEMPATH\/Cache\/CacheInterface.php","name":"CacheInterface.php"},{"path":"SYSTEMPATH\/Cache\/Handlers\/BaseHandler.php","name":"BaseHandler.php"},{"path":"SYSTEMPATH\/Cache\/Handlers\/FileHandler.php","name":"FileHandler.php"},{"path":"SYSTEMPATH\/Cache\/ResponseCache.php","name":"ResponseCache.php"},{"path":"SYSTEMPATH\/CodeIgniter.php","name":"CodeIgniter.php"},{"path":"SYSTEMPATH\/Common.php","name":"Common.php"},{"path":"SYSTEMPATH\/Config\/AutoloadConfig.php","name":"AutoloadConfig.php"},{"path":"SYSTEMPATH\/Config\/BaseConfig.php","name":"BaseConfig.php"},{"path":"SYSTEMPATH\/Config\/BaseService.php","name":"BaseService.php"},{"path":"SYSTEMPATH\/Config\/DotEnv.php","name":"DotEnv.php"},{"path":"SYSTEMPATH\/Config\/Factories.php","name":"Factories.php"},{"path":"SYSTEMPATH\/Config\/Factory.php","name":"Factory.php"},{"path":"SYSTEMPATH\/Config\/Filters.php","name":"Filters.php"},{"path":"SYSTEMPATH\/Config\/Routing.php","name":"Routing.php"},{"path":"SYSTEMPATH\/Config\/Services.php","name":"Services.php"},{"path":"SYSTEMPATH\/Config\/View.php","name":"View.php"},{"path":"SYSTEMPATH\/Controller.php","name":"Controller.php"},{"path":"SYSTEMPATH\/Cookie\/CloneableCookieInterface.php","name":"CloneableCookieInterface.php"},{"path":"SYSTEMPATH\/Cookie\/Cookie.php","name":"Cookie.php"},{"path":"SYSTEMPATH\/Cookie\/CookieInterface.php","name":"CookieInterface.php"},{"path":"SYSTEMPATH\/Cookie\/CookieStore.php","name":"CookieStore.php"},{"path":"SYSTEMPATH\/Database\/BaseBuilder.php","name":"BaseBuilder.php"},{"path":"SYSTEMPATH\/Database\/BaseConnection.php","name":"BaseConnection.php"},{"path":"SYSTEMPATH\/Database\/BaseResult.php","name":"BaseResult.php"},{"path":"SYSTEMPATH\/Database\/Config.php","name":"Config.php"},{"path":"SYSTEMPATH\/Database\/ConnectionInterface.php","name":"ConnectionInterface.php"},{"path":"SYSTEMPATH\/Database\/Database.php","name":"Database.php"},{"path":"SYSTEMPATH\/Database\/MySQLi\/Builder.php","name":"Builder.php"},{"path":"SYSTEMPATH\/Database\/MySQLi\/Connection.php","name":"Connection.php"},{"path":"SYSTEMPATH\/Database\/MySQLi\/Result.php","name":"Result.php"},{"path":"SYSTEMPATH\/Database\/Query.php","name":"Query.php"},{"path":"SYSTEMPATH\/Database\/QueryInterface.php","name":"QueryInterface.php"},{"path":"SYSTEMPATH\/Database\/ResultInterface.php","name":"ResultInterface.php"},{"path":"SYSTEMPATH\/Debug\/Exceptions.php","name":"Exceptions.php"},{"path":"SYSTEMPATH\/Debug\/Timer.php","name":"Timer.php"},{"path":"SYSTEMPATH\/Debug\/Toolbar.php","name":"Toolbar.php"},{"path":"SYSTEMPATH\/Debug\/Toolbar\/Collectors\/BaseCollector.php","name":"BaseCollector.php"},{"path":"SYSTEMPATH\/Debug\/Toolbar\/Collectors\/Database.php","name":"Database.php"},{"path":"SYSTEMPATH\/Debug\/Toolbar\/Collectors\/Events.php","name":"Events.php"},{"path":"SYSTEMPATH\/Debug\/Toolbar\/Collectors\/Files.php","name":"Files.php"},{"path":"SYSTEMPATH\/Debug\/Toolbar\/Collectors\/Logs.php","name":"Logs.php"},{"path":"SYSTEMPATH\/Debug\/Toolbar\/Collectors\/Routes.php","name":"Routes.php"},{"path":"SYSTEMPATH\/Debug\/Toolbar\/Collectors\/Timers.php","name":"Timers.php"},{"path":"SYSTEMPATH\/Debug\/Toolbar\/Collectors\/Views.php","name":"Views.php"},{"path":"SYSTEMPATH\/Events\/Events.php","name":"Events.php"},{"path":"SYSTEMPATH\/Filters\/DebugToolbar.php","name":"DebugToolbar.php"},{"path":"SYSTEMPATH\/Filters\/FilterInterface.php","name":"FilterInterface.php"},{"path":"SYSTEMPATH\/Filters\/Filters.php","name":"Filters.php"},{"path":"SYSTEMPATH\/Filters\/ForceHTTPS.php","name":"ForceHTTPS.php"},{"path":"SYSTEMPATH\/Filters\/PageCache.php","name":"PageCache.php"},{"path":"SYSTEMPATH\/Filters\/PerformanceMetrics.php","name":"PerformanceMetrics.php"},{"path":"SYSTEMPATH\/Format\/Format.php","name":"Format.php"},{"path":"SYSTEMPATH\/Format\/FormatterInterface.php","name":"FormatterInterface.php"},{"path":"SYSTEMPATH\/Format\/JSONFormatter.php","name":"JSONFormatter.php"},{"path":"SYSTEMPATH\/HTTP\/ContentSecurityPolicy.php","name":"ContentSecurityPolicy.php"},{"path":"SYSTEMPATH\/HTTP\/Header.php","name":"Header.php"},{"path":"SYSTEMPATH\/HTTP\/IncomingRequest.php","name":"IncomingRequest.php"},{"path":"SYSTEMPATH\/HTTP\/Message.php","name":"Message.php"},{"path":"SYSTEMPATH\/HTTP\/MessageInterface.php","name":"MessageInterface.php"},{"path":"SYSTEMPATH\/HTTP\/MessageTrait.php","name":"MessageTrait.php"},{"path":"SYSTEMPATH\/HTTP\/Method.php","name":"Method.php"},{"path":"SYSTEMPATH\/HTTP\/OutgoingRequest.php","name":"OutgoingRequest.php"},{"path":"SYSTEMPATH\/HTTP\/OutgoingRequestInterface.php","name":"OutgoingRequestInterface.php"},{"path":"SYSTEMPATH\/HTTP\/Request.php","name":"Request.php"},{"path":"SYSTEMPATH\/HTTP\/RequestInterface.php","name":"RequestInterface.php"},{"path":"SYSTEMPATH\/HTTP\/RequestTrait.php","name":"RequestTrait.php"},{"path":"SYSTEMPATH\/HTTP\/Response.php","name":"Response.php"},{"path":"SYSTEMPATH\/HTTP\/ResponseInterface.php","name":"ResponseInterface.php"},{"path":"SYSTEMPATH\/HTTP\/ResponseTrait.php","name":"ResponseTrait.php"},{"path":"SYSTEMPATH\/HTTP\/SiteURI.php","name":"SiteURI.php"},{"path":"SYSTEMPATH\/HTTP\/SiteURIFactory.php","name":"SiteURIFactory.php"},{"path":"SYSTEMPATH\/HTTP\/URI.php","name":"URI.php"},{"path":"SYSTEMPATH\/HTTP\/UserAgent.php","name":"UserAgent.php"},{"path":"SYSTEMPATH\/Helpers\/array_helper.php","name":"array_helper.php"},{"path":"SYSTEMPATH\/Helpers\/kint_helper.php","name":"kint_helper.php"},{"path":"SYSTEMPATH\/Helpers\/url_helper.php","name":"url_helper.php"},{"path":"SYSTEMPATH\/I18n\/Time.php","name":"Time.php"},{"path":"SYSTEMPATH\/I18n\/TimeTrait.php","name":"TimeTrait.php"},{"path":"SYSTEMPATH\/Log\/Handlers\/BaseHandler.php","name":"BaseHandler.php"},{"path":"SYSTEMPATH\/Log\/Handlers\/FileHandler.php","name":"FileHandler.php"},{"path":"SYSTEMPATH\/Log\/Handlers\/HandlerInterface.php","name":"HandlerInterface.php"},{"path":"SYSTEMPATH\/Log\/Logger.php","name":"Logger.php"},{"path":"SYSTEMPATH\/Model.php","name":"Model.php"},{"path":"SYSTEMPATH\/Modules\/Modules.php","name":"Modules.php"},{"path":"SYSTEMPATH\/Router\/AutoRouter.php","name":"AutoRouter.php"},{"path":"SYSTEMPATH\/Router\/AutoRouterInterface.php","name":"AutoRouterInterface.php"},{"path":"SYSTEMPATH\/Router\/RouteCollection.php","name":"RouteCollection.php"},{"path":"SYSTEMPATH\/Router\/RouteCollectionInterface.php","name":"RouteCollectionInterface.php"},{"path":"SYSTEMPATH\/Router\/Router.php","name":"Router.php"},{"path":"SYSTEMPATH\/Router\/RouterInterface.php","name":"RouterInterface.php"},{"path":"SYSTEMPATH\/Superglobals.php","name":"Superglobals.php"},{"path":"SYSTEMPATH\/Traits\/ConditionalTrait.php","name":"ConditionalTrait.php"},{"path":"SYSTEMPATH\/View\/RendererInterface.php","name":"RendererInterface.php"},{"path":"SYSTEMPATH\/View\/View.php","name":"View.php"},{"path":"SYSTEMPATH\/View\/ViewDecoratorTrait.php","name":"ViewDecoratorTrait.php"}],"userFiles":[{"path":"APPPATH\/Common.php","name":"Common.php"},{"path":"APPPATH\/Config\/App.php","name":"App.php"},{"path":"APPPATH\/Config\/Autoload.php","name":"Autoload.php"},{"path":"APPPATH\/Config\/Boot\/development.php","name":"development.php"},{"path":"APPPATH\/Config\/Cache.php","name":"Cache.php"},{"path":"APPPATH\/Config\/Constants.php","name":"Constants.php"},{"path":"APPPATH\/Config\/ContentSecurityPolicy.php","name":"ContentSecurityPolicy.php"},{"path":"APPPATH\/Config\/Cookie.php","name":"Cookie.php"},{"path":"APPPATH\/Config\/Database.php","name":"Database.php"},{"path":"APPPATH\/Config\/Events.php","name":"Events.php"},{"path":"APPPATH\/Config\/Exceptions.php","name":"Exceptions.php"},{"path":"APPPATH\/Config\/Feature.php","name":"Feature.php"},{"path":"APPPATH\/Config\/Filters.php","name":"Filters.php"},{"path":"APPPATH\/Config\/Format.php","name":"Format.php"},{"path":"APPPATH\/Config\/Kint.php","name":"Kint.php"},{"path":"APPPATH\/Config\/Logger.php","name":"Logger.php"},{"path":"APPPATH\/Config\/Modules.php","name":"Modules.php"},{"path":"APPPATH\/Config\/Optimize.php","name":"Optimize.php"},{"path":"APPPATH\/Config\/Paths.php","name":"Paths.php"},{"path":"APPPATH\/Config\/Routes.php","name":"Routes.php"},{"path":"APPPATH\/Config\/Routing.php","name":"Routing.php"},{"path":"APPPATH\/Config\/Services.php","name":"Services.php"},{"path":"APPPATH\/Config\/Toolbar.php","name":"Toolbar.php"},{"path":"APPPATH\/Config\/UserAgents.php","name":"UserAgents.php"},{"path":"APPPATH\/Config\/View.php","name":"View.php"},{"path":"APPPATH\/Controllers\/LotteryData.php","name":"LotteryData.php"},{"path":"APPPATH\/Models\/LotteryModel.php","name":"LotteryModel.php"},{"path":"APPPATH\/Models\/SettingsModel.php","name":"SettingsModel.php"},{"path":"FCPATH\/index.php","name":"index.php"},{"path":"VENDORPATH\/autoload.php","name":"autoload.php"},{"path":"VENDORPATH\/composer\/ClassLoader.php","name":"ClassLoader.php"},{"path":"VENDORPATH\/composer\/InstalledVersions.php","name":"InstalledVersions.php"},{"path":"VENDORPATH\/composer\/autoload_real.php","name":"autoload_real.php"},{"path":"VENDORPATH\/composer\/autoload_static.php","name":"autoload_static.php"},{"path":"VENDORPATH\/composer\/installed.php","name":"installed.php"},{"path":"VENDORPATH\/composer\/platform_check.php","name":"platform_check.php"},{"path":"VENDORPATH\/google\/apiclient-services\/autoload.php","name":"autoload.php"},{"path":"VENDORPATH\/google\/apiclient\/src\/AccessToken\/Revoke.php","name":"Revoke.php"},{"path":"VENDORPATH\/google\/apiclient\/src\/AccessToken\/Verify.php","name":"Verify.php"},{"path":"VENDORPATH\/google\/apiclient\/src\/AuthHandler\/AuthHandlerFactory.php","name":"AuthHandlerFactory.php"},{"path":"VENDORPATH\/google\/apiclient\/src\/AuthHandler\/Guzzle6AuthHandler.php","name":"Guzzle6AuthHandler.php"},{"path":"VENDORPATH\/google\/apiclient\/src\/AuthHandler\/Guzzle7AuthHandler.php","name":"Guzzle7AuthHandler.php"},{"path":"VENDORPATH\/google\/apiclient\/src\/Client.php","name":"Client.php"},{"path":"VENDORPATH\/google\/apiclient\/src\/Collection.php","name":"Collection.php"},{"path":"VENDORPATH\/google\/apiclient\/src\/Exception.php","name":"Exception.php"},{"path":"VENDORPATH\/google\/apiclient\/src\/Http\/Batch.php","name":"Batch.php"},{"path":"VENDORPATH\/google\/apiclient\/src\/Http\/MediaFileUpload.php","name":"MediaFileUpload.php"},{"path":"VENDORPATH\/google\/apiclient\/src\/Http\/REST.php","name":"REST.php"},{"path":"VENDORPATH\/google\/apiclient\/src\/Model.php","name":"Model.php"},{"path":"VENDORPATH\/google\/apiclient\/src\/Service.php","name":"Service.php"},{"path":"VENDORPATH\/google\/apiclient\/src\/Service\/Exception.php","name":"Exception.php"},{"path":"VENDORPATH\/google\/apiclient\/src\/Service\/Resource.php","name":"Resource.php"},{"path":"VENDORPATH\/google\/apiclient\/src\/Task\/Composer.php","name":"Composer.php"},{"path":"VENDORPATH\/google\/apiclient\/src\/Task\/Exception.php","name":"Exception.php"},{"path":"VENDORPATH\/google\/apiclient\/src\/Task\/Retryable.php","name":"Retryable.php"},{"path":"VENDORPATH\/google\/apiclient\/src\/Task\/Runner.php","name":"Runner.php"},{"path":"VENDORPATH\/google\/apiclient\/src\/Utils\/UriTemplate.php","name":"UriTemplate.php"},{"path":"VENDORPATH\/google\/apiclient\/src\/aliases.php","name":"aliases.php"},{"path":"VENDORPATH\/guzzlehttp\/guzzle\/src\/functions.php","name":"functions.php"},{"path":"VENDORPATH\/guzzlehttp\/guzzle\/src\/functions_include.php","name":"functions_include.php"},{"path":"VENDORPATH\/kint-php\/kint\/init.php","name":"init.php"},{"path":"VENDORPATH\/kint-php\/kint\/init_helpers.php","name":"init_helpers.php"},{"path":"VENDORPATH\/kint-php\/kint\/src\/FacadeInterface.php","name":"FacadeInterface.php"},{"path":"VENDORPATH\/kint-php\/kint\/src\/Kint.php","name":"Kint.php"},{"path":"VENDORPATH\/kint-php\/kint\/src\/Renderer\/AbstractRenderer.php","name":"AbstractRenderer.php"},{"path":"VENDORPATH\/kint-php\/kint\/src\/Renderer\/CliRenderer.php","name":"CliRenderer.php"},{"path":"VENDORPATH\/kint-php\/kint\/src\/Renderer\/RendererInterface.php","name":"RendererInterface.php"},{"path":"VENDORPATH\/kint-php\/kint\/src\/Renderer\/RichRenderer.php","name":"RichRenderer.php"},{"path":"VENDORPATH\/kint-php\/kint\/src\/Renderer\/TextRenderer.php","name":"TextRenderer.php"},{"path":"VENDORPATH\/kint-php\/kint\/src\/Utils.php","name":"Utils.php"},{"path":"VENDORPATH\/laminas\/laminas-escaper\/src\/Escaper.php","name":"Escaper.php"},{"path":"VENDORPATH\/myclabs\/deep-copy\/src\/DeepCopy\/deep_copy.php","name":"deep_copy.php"},{"path":"VENDORPATH\/phpseclib\/phpseclib\/phpseclib\/bootstrap.php","name":"bootstrap.php"},{"path":"VENDORPATH\/phpunit\/phpunit\/src\/Framework\/Assert\/Functions.php","name":"Functions.php"},{"path":"VENDORPATH\/psr\/log\/src\/LogLevel.php","name":"LogLevel.php"},{"path":"VENDORPATH\/psr\/log\/src\/LoggerInterface.php","name":"LoggerInterface.php"},{"path":"VENDORPATH\/ralouphie\/getallheaders\/src\/getallheaders.php","name":"getallheaders.php"},{"path":"VENDORPATH\/react\/promise\/src\/functions.php","name":"functions.php"},{"path":"VENDORPATH\/react\/promise\/src\/functions_include.php","name":"functions_include.php"},{"path":"VENDORPATH\/symfony\/deprecation-contracts\/function.php","name":"function.php"},{"path":"VENDORPATH\/symfony\/polyfill-ctype\/bootstrap.php","name":"bootstrap.php"},{"path":"VENDORPATH\/symfony\/polyfill-ctype\/bootstrap80.php","name":"bootstrap80.php"},{"path":"VENDORPATH\/symfony\/polyfill-intl-grapheme\/bootstrap.php","name":"bootstrap.php"},{"path":"VENDORPATH\/symfony\/polyfill-intl-normalizer\/bootstrap.php","name":"bootstrap.php"},{"path":"VENDORPATH\/symfony\/polyfill-intl-normalizer\/bootstrap80.php","name":"bootstrap80.php"},{"path":"VENDORPATH\/symfony\/polyfill-mbstring\/bootstrap.php","name":"bootstrap.php"},{"path":"VENDORPATH\/symfony\/polyfill-mbstring\/bootstrap80.php","name":"bootstrap80.php"},{"path":"VENDORPATH\/symfony\/polyfill-php80\/bootstrap.php","name":"bootstrap.php"},{"path":"VENDORPATH\/symfony\/polyfill-php81\/bootstrap.php","name":"bootstrap.php"},{"path":"VENDORPATH\/symfony\/string\/Resources\/functions.php","name":"functions.php"}]},"badgeValue":192,"isEmpty":false,"hasTabContent":true,"hasLabel":false,"icon":"data:image\/png;base64,iVBORw0KGgoAAAANSUhEUgAAABgAAAAYCAYAAADgdz34AAAAAXNSR0IArs4c6QAAAARnQU1BAACxjwv8YQUAAAAJcEhZcwAADsMAAA7DAcdvqGQAAAGBSURBVEhL7ZQ9S8NQGIVTBQUncfMfCO4uLgoKbuKQOWg+OkXERRE1IAXrIHbVDrqIDuLiJgj+gro7S3dnpfq88b1FMTE3VZx64HBzzvvZWxKnj15QCcPwCD5HUfSWR+JtzgmtsUcQBEva5IIm9SwSu+95CAWbUuy67qBa32ByZEDpIaZYZSZMjjQuPcQUq8yEyYEb8FSerYeQVGbAFzJkX1PyQWLhgCz0BxTCekC1Wp0hsa6yokzhed4oje6Iz6rlJEkyIKfUEFtITVtQdAibn5rMyaYsMS+a5wTv8qeXMhcU16QZbKgl3hbs+L4\/pnpdc87MElZgq10p5DxGdq8I7xrvUWUKvG3NbSK7ubngYzdJwSsF7TiOh9VOgfcEz1UayNe3JUPM1RWC5GXYgTfc75B4NBmXJnAtTfpABX0iPvEd9ezALwkplCFXcr9styiNOKc1RRZpaPM9tcqBwlWzGY1qPL9wjqRBgF5BH6j8HWh2S7MHlX8PrmbK+k\/8PzjOOzx1D3i1pKTTAAAAAElFTkSuQmCC","hasTimelineData":false,"timelineData":[]},{"title":"Routes","titleSafe":"routes","titleDetails":"","display":{"matchedRoute":[{"directory":"","controller":"\\App\\Controllers\\LotteryData","method":"fetchAll","paramCount":0,"truePCount":0,"params":[]}],"routes":[{"method":"GET","route":"\/","handler":"\\App\\Controllers\\Home::index"},{"method":"GET","route":"malaysia-4d-results","handler":"\\App\\Controllers\\Home::myresultsindex"},{"method":"GET","route":"sabah-sarawak-4d-results","handler":"\\App\\Controllers\\Home::westmyresultsindex"},{"method":"GET","route":"singapore-4d-results","handler":"\\App\\Controllers\\Home::singaporeresultsindex"},{"method":"GET","route":"cambodia-4d-results","handler":"\\App\\Controllers\\Home::cambodiaresultsindex"},{"method":"GET","route":"results\/magnum","handler":"\\App\\Controllers\\Home::myresultsindex\/magnum"},{"method":"GET","route":"results\/damacai","handler":"\\App\\Controllers\\Home::myresultsindex\/damacai"},{"method":"GET","route":"results\/toto","handler":"\\App\\Controllers\\Home::myresultsindex\/toto"},{"method":"GET","route":"results\/singapore-pools","handler":"\\App\\Controllers\\Home::singaporeresultsindex\/singapore-pools"},{"method":"GET","route":"results\/sabah-88","handler":"\\App\\Controllers\\Home::westmyresultsindex\/sabah"},{"method":"GET","route":"results\/sandakan","handler":"\\App\\Controllers\\Home::westmyresultsindex\/sandakan"},{"method":"GET","route":"results\/sarawak","handler":"\\App\\Controllers\\Home::westmyresultsindex\/sarawak"},{"method":"GET","route":"results\/gd-lotto","handler":"\\App\\Controllers\\Home::cambodiaresultsindex\/gd"},{"method":"GET","route":"results\/perdana","handler":"\\App\\Controllers\\Home::cambodiaresultsindex\/perdana"},{"method":"GET","route":"results\/lucky-hari","handler":"\\App\\Controllers\\Home::cambodiaresultsindex\/lucky"},{"method":"GET","route":"results\/lotto-macao","handler":"\\App\\Controllers\\Home::othersresultsindex\/lmc"},{"method":"GET","route":"results\/matahari","handler":"\\App\\Controllers\\Home::othersresultsindex\/mth"},{"method":"GET","route":"results\/9-lotto","handler":"\\App\\Controllers\\Home::cambodiaresultsindex\/nlt"},{"method":"GET","route":"fetchall","handler":"\\App\\Controllers\\LotteryData::fetchAll"},{"method":"GET","route":"past-results","handler":"\\App\\Controllers\\LotteryData::past_results_index"},{"method":"GET","route":"past-results\/([^\/]+)","handler":"\\App\\Controllers\\LotteryData::past_results_by_date\/$1"},{"method":"GET","route":"fetchpastresults","handler":"\\App\\Controllers\\LotteryData::fetch_past_results"},{"method":"GET","route":"estimated-jackpot","handler":"\\App\\Controllers\\Home::estimatedJackpotsIndex"},{"method":"GET","route":"4d-special-draw","handler":"\\App\\Controllers\\Home::specialDrawIndex"},{"method":"GET","route":"recent-news","handler":"\\App\\Controllers\\PostController::viewRecentNewsIndex"},{"method":"GET","route":"4d-result-api","handler":"\\App\\Controllers\\PostController::view\/4d-result-api"},{"method":"GET","route":"history","handler":"\\App\\Controllers\\SearchController::index"},{"method":"GET","route":"history\/([0-9]+)","handler":"\\App\\Controllers\\SearchController::numberIndex\/$1"},{"method":"GET","route":"dictionary","handler":"\\App\\Controllers\\SearchController::meaningIndex"},{"method":"GET","route":"dictionary\/([^\/]+)","handler":"\\App\\Controllers\\SearchController::wordIndex\/$1"},{"method":"GET","route":"hot-number","handler":"\\App\\Controllers\\SearchController::hotnumberIndex"},{"method":"GET","route":"fetchhistoryresults","handler":"\\App\\Controllers\\SearchController::fetchhistoryresultsIndex"},{"method":"GET","route":"4d-prediction","handler":"\\App\\Controllers\\OtherPagesController::predictionIndex"},{"method":"GET","route":"api","handler":"\\App\\Controllers\\ApiController::apiIndex"},{"method":"GET","route":"disclaimer","handler":"\\App\\Controllers\\PostController::view\/disclaimer"},{"method":"GET","route":"privacy-policy","handler":"\\App\\Controllers\\PostController::view\/privacy-policy"},{"method":"GET","route":"faq","handler":"\\App\\Controllers\\PostController::view\/faq"},{"method":"GET","route":"about-us","handler":"\\App\\Controllers\\PostController::view\/about-us"},{"method":"GET","route":"contact-us","handler":"\\App\\Controllers\\PostController::view\/contact-us"},{"method":"GET","route":"sitemap\\.xml","handler":"\\App\\Controllers\\OtherPagesController::sitemapIndex"},{"method":"GET","route":"admin\/settings","handler":"\\App\\Controllers\\Admin\\SettingsController::index"},{"method":"GET","route":"admin\/lottery","handler":"\\App\\Controllers\\Admin\\SettingsController::lotteryIndex"},{"method":"GET","route":"admin\/number-pages","handler":"\\App\\Controllers\\Admin\\SettingsController::numberPagesIndex"},{"method":"GET","route":"admin\/sitemap","handler":"\\App\\Controllers\\Admin\\SettingsController::sitemapAdminIndex"},{"method":"GET","route":"admin\/posts","handler":"\\App\\Controllers\\PostController::index"},{"method":"GET","route":"admin\/posts\/create","handler":"\\App\\Controllers\\PostController::create"},{"method":"GET","route":"admin\/posts\/edit\/([0-9]+)","handler":"\\App\\Controllers\\PostController::edit\/$1"},{"method":"GET","route":"admin\/posts\/delete\/([0-9]+)","handler":"\\App\\Controllers\\PostController::delete\/$1"},{"method":"GET","route":"recent-news\/(.*)","handler":"\\App\\Controllers\\PostController::view\/$1"},{"method":"GET","route":"posts\/(.*)","handler":"\\App\\Controllers\\PostController::view\/$1"},{"method":"GET","route":"admin\/login","handler":"\\App\\Controllers\\AuthController::index"},{"method":"GET","route":"admin\/logout","handler":"\\App\\Controllers\\AuthController::logout"},{"method":"GET","route":"admin\/dashboard","handler":"\\App\\Controllers\\DashboardController::index"},{"method":"GET","route":"admin\/users","handler":"\\App\\Controllers\\UserController::index"},{"method":"GET","route":"admin\/users\/create","handler":"\\App\\Controllers\\UserController::create"},{"method":"GET","route":"admin\/users\/edit\/([0-9]+)","handler":"\\App\\Controllers\\UserController::edit\/$1"},{"method":"GET","route":"admin\/users\/delete\/([0-9]+)","handler":"\\App\\Controllers\\UserController::delete\/$1"},{"method":"GET","route":"admin\/categories","handler":"\\App\\Controllers\\CategoryController::index"},{"method":"GET","route":"admin\/categories\/create","handler":"\\App\\Controllers\\CategoryController::create"},{"method":"GET","route":"admin\/categories\/edit\/([0-9]+)","handler":"\\App\\Controllers\\CategoryController::edit\/$1"},{"method":"GET","route":"admin\/categories\/delete\/([0-9]+)","handler":"\\App\\Controllers\\CategoryController::delete\/$1"},{"method":"GET","route":"admin\/elfinder\/connector","handler":"\\App\\Controllers\\ElfinderController::connector"},{"method":"GET","route":"admin\/elfinder\/upload","handler":"\\App\\Controllers\\ElfinderController::upload"},{"method":"GET","route":"api\/add_favourite_numbers","handler":"\\App\\Controllers\\MobileAPIController::addFavouriteNumbers"},{"method":"GET","route":"api\/get_hot_numbers","handler":"\\App\\Controllers\\SearchController::apiHotNumbers"},{"method":"GET","route":"api\/get_4d_dictionary\/(.*)","handler":"\\App\\Controllers\\SearchController::api4DDictionary\/$1"},{"method":"GET","route":"api\/get_estimated_jackpots","handler":"\\App\\Controllers\\Home::apiEstimatedJackpots"},{"method":"GET","route":"api\/fetchall","handler":"\\App\\Controllers\\LotteryData::fetchAll"},{"method":"GET","route":"api\/getdates","handler":"\\App\\Controllers\\LotteryData::getDates"},{"method":"GET","route":"api\/getdates\/([^\/]+)","handler":"\\App\\Controllers\\LotteryData::getDatesByMonthYear\/$1"},{"method":"GET","route":"api\/fetchall\/([^\/]+)","handler":"\\App\\Controllers\\LotteryData::getLotteryByDate\/$1"},{"method":"POST","route":"fetchpastresults","handler":"\\App\\Controllers\\LotteryData::fetch_past_results"},{"method":"POST","route":"fetchall","handler":"\\App\\Controllers\\LotteryData::fetchAll"},{"method":"POST","route":"fetchhistoryresults","handler":"\\App\\Controllers\\SearchController::fetchhistoryresultsIndex"},{"method":"POST","route":"admin\/settings\/save","handler":"\\App\\Controllers\\Admin\\SettingsController::save"},{"method":"POST","route":"admin\/lottery\/savelottery","handler":"\\App\\Controllers\\Admin\\SettingsController::saveLottery"},{"method":"POST","route":"admin\/settings\/saveNumberPage","handler":"\\App\\Controllers\\Admin\\SettingsController::saveNumberPage"},{"method":"POST","route":"admin\/sitemap\/saveSitemap","handler":"\\App\\Controllers\\Admin\\SettingsController::saveSitemap"},{"method":"POST","route":"admin\/sitemap\/updateOrder","handler":"\\App\\Controllers\\Admin\\SettingsController::updateOrder"},{"method":"POST","route":"admin\/settings\/deleteOption","handler":"\\App\\Controllers\\Admin\\SettingsController::deleteOption"},{"method":"POST","route":"admin\/posts\/store","handler":"\\App\\Controllers\\PostController::store"},{"method":"POST","route":"admin\/posts\/update\/([0-9]+)","handler":"\\App\\Controllers\\PostController::update\/$1"},{"method":"POST","route":"admin\/posts\/deleteImage","handler":"\\App\\Controllers\\PostController::deleteImage"},{"method":"POST","route":"login\/authenticate","handler":"\\App\\Controllers\\AuthController::authenticate"},{"method":"POST","route":"admin\/users\/store","handler":"\\App\\Controllers\\UserController::store"},{"method":"POST","route":"admin\/users\/update\/([0-9]+)","handler":"\\App\\Controllers\\UserController::update\/$1"},{"method":"POST","route":"admin\/categories\/store","handler":"\\App\\Controllers\\CategoryController::store"},{"method":"POST","route":"admin\/categories\/update\/([0-9]+)","handler":"\\App\\Controllers\\CategoryController::update\/$1"},{"method":"POST","route":"admin\/elfinder\/connector","handler":"\\App\\Controllers\\ElfinderController::connector"},{"method":"POST","route":"admin\/elfinder\/upload","handler":"\\App\\Controllers\\ElfinderController::upload"},{"method":"POST","route":"api\/save_notification_settings","handler":"\\App\\Controllers\\MobileAPIController::saveNotificationSettings"},{"method":"POST","route":"api\/add_favourite_numbers","handler":"\\App\\Controllers\\MobileAPIController::addFavouriteNumbers"},{"method":"POST","route":"api\/remove_favourite_number","handler":"\\App\\Controllers\\MobileAPIController::removeFavouriteNumber"},{"method":"POST","route":"api\/fetch_number_history","handler":"\\App\\Controllers\\SearchController::apiNumberHistory"},{"method":"CLI","route":"lottery:fetch","handler":"\\App\\Controllers\\FetchLotteryData"},{"method":"CLI","route":"lottery:specialcashsweep","handler":"\\App\\Controllers\\FetchSpecialCashSweep"},{"method":"CLI","route":"lottery:magnum","handler":"\\App\\Controllers\\FetchMagnum"},{"method":"CLI","route":"lottery:fetchtoto","handler":"\\App\\Controllers\\FetchToto"},{"method":"CLI","route":"lottery:fetch9toto","handler":"\\App\\Controllers\\FetchNineToto"},{"method":"CLI","route":"lottery:fetchsingaporepools","handler":"\\App\\Controllers\\FetchSingaporePools"},{"method":"CLI","route":"lottery:fetchsandakan","handler":"\\App\\Controllers\\FetchSandakan"}]},"badgeValue":72,"isEmpty":false,"hasTabContent":true,"hasLabel":false,"icon":"data:image\/png;base64,iVBORw0KGgoAAAANSUhEUgAAABgAAAAYCAYAAADgdz34AAAAAXNSR0IArs4c6QAAAARnQU1BAACxjwv8YQUAAAAJcEhZcwAADsMAAA7DAcdvqGQAAAFDSURBVEhL7ZRNSsNQFIUjVXSiOFEcuQIHDpzpxC0IGYeE\/BEInbWlCHEDLsSiuANdhKDjgm6ggtSJ+l25ldrmmTwIgtgDh\/t37r1J+16cX0dRFMtpmu5pWAkrvYjjOB7AETzStBFW+inxu3KUJMmhludQpoflS1zXban4LYqiO224h6VLTHr8Z+z8EpIHFF9gG78nDVmW7UgTHKjsCyY98QP+pcq+g8Ku2s8G8X3f3\/I8b038WZTp+bO38zxfFd+I6YY6sNUvFlSDk9CRhiAI1jX1I9Cfw7GG1UB8LAuwbU0ZwQnbRDeEN5qqBxZMLtE1ti9LtbREnMIuOXnyIf5rGIb7Wq8HmlZgwYBH7ORTcKH5E4mpjeGt9fBZcHE2GCQ3Vt7oTNPNg+FXLHnSsHkw\/FR+Gg2bB8Ptzrst\/v6C\/wrH+QB+duli6MYJdQAAAABJRU5ErkJggg==","hasTimelineData":false,"timelineData":[]},{"title":"Events","titleSafe":"events","titleDetails":"","display":{"events":{"pre_system":{"event":"pre_system","duration":"0.64","count":1},"dbquery":{"event":"dbquery","duration":"1.66","count":20}}},"badgeValue":21,"isEmpty":false,"hasTabContent":true,"hasLabel":false,"icon":"data:image\/png;base64,iVBORw0KGgoAAAANSUhEUgAAABgAAAAYCAYAAADgdz34AAAAAXNSR0IArs4c6QAAAARnQU1BAACxjwv8YQUAAAAJcEhZcwAADsMAAA7DAcdvqGQAAAEASURBVEhL7ZXNDcIwDIVTsRBH1uDQDdquUA6IM1xgCA6MwJUN2hk6AQzAz0vl0ETUxC5VT3zSU5w81\/mRMGZysixbFEVR0jSKNt8geQU9aRpFmp\/keX6AbjZ5oB74vsaN5lSzA4tLSjpBFxsjeSuRy4d2mDdQTWU7YLbXTNN05mKyovj5KL6B7q3hoy3KwdZxBlT+Ipz+jPHrBqOIynZgcZonoukb\/0ckiTHqNvDXtXEAaygRbaB9FvUTjRUHsIYS0QaSp+Dw6wT4hiTmYHOcYZsdLQ2CbXa4ftuuYR4x9vYZgdb4vsFYUdmABMYeukK9\/SUme3KMFQ77+Yfzh8eYF8+orDuDWU5LAAAAAElFTkSuQmCC","hasTimelineData":true,"timelineData":[{"name":"Event: pre_system","component":"Events","start":1760363906.376627,"duration":0.0006380081176757812},{"name":"Event: dbquery","component":"Events","start":1760363906.400505,"duration":4.982948303222656e-5},{"name":"Event: dbquery","component":"Events","start":1760363906.401447,"duration":3.0994415283203125e-5},{"name":"Event: dbquery","component":"Events","start":1760363906.402128,"duration":2.9087066650390625e-5},{"name":"Event: dbquery","component":"Events","start":1760363906.403472,"duration":2.8133392333984375e-5},{"name":"Event: dbquery","component":"Events","start":1760363906.404088,"duration":1.9073486328125e-5},{"name":"Event: dbquery","component":"Events","start":1760363906.404548,"duration":2.002716064453125e-5},{"name":"Event: dbquery","component":"Events","start":1760363906.409919,"duration":5.1021575927734375e-5},{"name":"Event: dbquery","component":"Events","start":1760363906.410752,"duration":3.790855407714844e-5},{"name":"Event: dbquery","component":"Events","start":1760363906.41305,"duration":0.0009071826934814453},{"name":"Event: dbquery","component":"Events","start":1760363906.416794,"duration":6.29425048828125e-5},{"name":"Event: dbquery","component":"Events","start":1760363906.420618,"duration":5.4836273193359375e-5},{"name":"Event: dbquery","component":"Events","start":1760363906.422477,"duration":5.1975250244140625e-5},{"name":"Event: dbquery","component":"Events","start":1760363906.423185,"duration":3.4809112548828125e-5},{"name":"Event: dbquery","component":"Events","start":1760363906.423746,"duration":2.8848648071289062e-5},{"name":"Event: dbquery","component":"Events","start":1760363906.424198,"duration":2.09808349609375e-5},{"name":"Event: dbquery","component":"Events","start":1760363906.42461,"duration":2.3126602172851562e-5},{"name":"Event: dbquery","component":"Events","start":1760363906.430626,"duration":5.817413330078125e-5},{"name":"Event: dbquery","component":"Events","start":1760363906.45842,"duration":5.888938903808594e-5},{"name":"Event: dbquery","component":"Events","start":1760363906.462612,"duration":6.008148193359375e-5},{"name":"Event: dbquery","component":"Events","start":1760363906.463466,"duration":3.409385681152344e-5}]}],"vars":{"varData":{"View Data":[]},"headers":{"Host":"4dpanda.com","User-Agent":"Dart\/3.5 (dart:io)","Cf-Ray":"98df5a0bd9e40911-SIN","Accept-Encoding":"gzip, br","Cdn-Loop":"cloudflare; loops=1","Cf-Connecting-Ip":"113.211.128.195","Cf-Ipcountry":"MY","Cf-Visitor":"{&quot;scheme&quot;:&quot;https&quot;}","X-Forwarded-Proto":"https","X-Forwarded-For":"113.211.128.195","Connection":"Keep-Alive"},"request":"HTTPS\/1.1","response":{"statusCode":200,"reason":"OK","contentType":"application\/json; charset=UTF-8","headers":{"Cache-Control":"no-store, max-age=0, no-cache","Content-Type":"application\/json; charset=UTF-8"}}},"config":{"ciVersion":"4.5.1","phpVersion":"8.2.20","phpSAPI":"apache2handler","environment":"development","baseURL":"https:\/\/4dpanda.com\/","timezone":"UTC","locale":"en","cspEnabled":false}}